PartA4/ex1_testb.v
`timescale 1 ns / 1ps
module ex1_testb;
	reg CLK, a;
	ex1 x1(CLK, a, y);
	initial begin
		x1.S0 = 0;
		x1.S1 = 0;
		CLK = 0;
		a = 0;
		$dumpfile("ex1_testb.vcd");
		$dumpvars(0,ex1_testb);
		#1500000 $finish; // this is large enough to check when clock go over 1M 
	end

	always #30 CLK=~CLK; // increasing clock speed so the program reaches 1M faster

	always @(posedge CLK) begin
		if ($time <= 1000000) begin
			if ({x1.S1,x1.S0} == 2'b11) begin
				$display("%8d", $time," state:",x1.S1,x1.S0, "  (reached target)"); 
				$display("The number of clock cycles until reachable: ","%8d", $time);
				$finish; 
			end
			else begin
				$display("%8d", $time, " state:",x1.S1,x1.S0);
			end
			a = $random;
		end
		else begin
		$display("Timed out, unreachable for state: 11");
		$finish; 
		end
	end
endmodule


module ex1(clock,A,Y);
input clock;
input A;
output Y;
reg S0,S1;
wire X1,NS0,NS1;
and g0(X1,S0,S1);
and g1(NS1,A,X1);
not g2(NS0,X1);
and g3(Y,A,X1);
always @(posedge clock) begin
S1<=NS1;
S0<=NS0;
end
endmodule
//State:11

PartA4/ex1_testb.vcd
$date
	Tue Mar 09 16:39:30 2021
$end
$version
	Icarus Verilog
$end
$timescale
	1ps
$end
$scope module ex1_testb $end
$var wire 1 ! y $end
$var reg 1 " CLK $end
$var reg 1 # a $end
$scope module x1 $end
$var wire 1 # A $end
$var wire 1 $ NS0 $end
$var wire 1 % NS1 $end
$var wire 1 & X1 $end
$var wire 1 ! Y $end
$var wire 1 " clock $end
$var reg 1 ' S0 $end
$var reg 1 ( S1 $end
$upscope $end
$upscope $end
$enddefinitions $end
#0
$dumpvars
0(
0'
0&
0%
1$
0#
0"
0!
$end
#30000
1'
1"
#60000
0"
#90000
1#
1"
#120000
0"
#150000
1"
#180000
0"
#210000
1"
#240000
0"
#270000
1"
#300000
0"
#330000
1"
#360000
0"
#390000
1"
#420000
0"
#450000
0#
1"
#480000
0"
#510000
1#
1"
#540000
0"
#570000
1"
#600000
0"
#630000
0#
1"
#660000
0"
#690000
1#
1"
#720000
0"
#750000
1"
#780000
0"
#810000
0#
1"
#840000
0"
#870000
1#
1"
#900000
0"
#930000
0#
1"
#960000
0"
#990000
1#
1"
#1020000
0"
#1050000
0#
1"
#1080000
0"
#1110000
1#
1"
#1140000
0"
#1170000
1"
#1200000
0"
#1230000
0#
1"
#1260000
0"
#1290000
1#
1"
#1320000
0"
#1350000
0#
1"
#1380000
0"
#1410000
1"
#1440000
0"
#1470000
1"
#1500000
0"
#1530000
1#
1"
#1560000
0"
#1590000
0#
1"
#1620000
0"
#1650000
1#
1"
#1680000
0"
#1710000
1"
#1740000
0"
#1770000
1"
#1800000
0"
#1830000
1"
#1860000
0"
#1890000
0#
1"
#1920000
0"
#1950000
1"
#1980000
0"
#2010000
1"
#2040000
0"
#2070000
1"
#2100000
0"
#2130000
1#
1"
#2160000
0"
#2190000
0#
1"
#2220000
0"
#2250000
1#
1"
#2280000
0"
#2310000
1"
#2340000
0"
#2370000
1"
#2400000
0"
#2430000
1"
#2460000
0"
#2490000
1"
#2520000
0"
#2550000
0#
1"
#2580000
0"
#2610000
1"
#2640000
0"
#2670000
1#
1"
#2700000
0"
#2730000
1"
#2760000
0"
#2790000
1"
#2820000
0"
#2850000
0#
1"
#2880000
0"
#2910000
1"
#2940000
0"
#2970000
1"
#3000000
0"
#3030000
1"
#3060000
0"
#3090000
1"
#3120000
0"
#3150000
1#
1"
#3180000
0"
#3210000
0#
1"
#3240000
0"
#3270000
1"
#3300000
0"
#3330000
1#
1"
#3360000
0"
#3390000
1"
#3420000
0"
#3450000
0#
1"
#3480000
0"
#3510000
1"
#3540000
0"
#3570000
1"
#3600000
0"
#3630000
1"
#3660000
0"
#3690000
1"
#3720000
0"
#3750000
1#
1"
#3780000
0"
#3810000
1"
#3840000
0"
#3870000
1"
#3900000
0"
#3930000
1"
#3960000
0"
#3990000
1"
#4020000
0"
#4050000
0#
1"
#4080000
0"
#4110000
1"
#4140000
0"
#4170000
1#
1"
#4200000
0"
#4230000
1"
#4260000
0"
#4290000
1"
#4320000
0"
#4350000
0#
1"
#4380000
0"
#4410000
1"
#4440000
0"
#4470000
1#
1"
#4500000
0"
#4530000
1"
#4560000
0"
#4590000
0#
1"
#4620000
0"
#4650000
1#
1"
#4680000
0"
#4710000
1"
#4740000
0"
#4770000
0#
1"
#4800000
0"
#4830000
1#
1"
#4860000
0"
#4890000
1"
#4920000
0"
#4950000
1"
#4980000
0"
#5010000
0#
1"
#5040000
0"
#5070000
1#
1"
#5100000
0"
#5130000
1"
#5160000
0"
#5190000
0#
1"
#5220000
0"
#5250000
1"
#5280000
0"
#5310000
1"
#5340000
0"
#5370000
1"
#5400000
0"
#5430000
1#
1"
#5460000
0"
#5490000
1"
#5520000
0"
#5550000
0#
1"
#5580000
0"
#5610000
1"
#5640000
0"
#5670000
1#
1"
#5700000
0"
#5730000
1"
#5760000
0"
#5790000
1"
#5820000
0"
#5850000
1"
#5880000
0"
#5910000
1"
#5940000
0"
#5970000
0#
1"
#6000000
0"
#6030000
1#
1"
#6060000
0"
#6090000
1"
#6120000
0"
#6150000
1"
#6180000
0"
#6210000
0#
1"
#6240000
0"
#6270000
1"
#6300000
0"
#6330000
1"
#6360000
0"
#6390000
1"
#6420000
0"
#6450000
1"
#6480000
0"
#6510000
1"
#6540000
0"
#6570000
1"
#6600000
0"
#6630000
1#
1"
#6660000
0"
#6690000
1"
#6720000
0"
#6750000
1"
#6780000
0"
#6810000
1"
#6840000
0"
#6870000
1"
#6900000
0"
#6930000
0#
1"
#6960000
0"
#6990000
1#
1"
#7020000
0"
#7050000
1"
#7080000
0"
#7110000
0#
1"
#7140000
0"
#7170000
1"
#7200000
0"
#7230000
1#
1"
#7260000
0"
#7290000
1"
#7320000
0"
#7350000
0#
1"
#7380000
0"
#7410000
1#
1"
#7440000
0"
#7470000
1"
#7500000
0"
#7530000
1"
#7560000
0"
#7590000
1"
#7620000
0"
#7650000
0#
1"
#7680000
0"
#7710000
1"
#7740000
0"
#7770000
1"
#7800000
0"
#7830000
1#
1"
#7860000
0"
#7890000
0#
1"
#7920000
0"
#7950000
1"
#7980000
0"
#8010000
1"
#8040000
0"
#8070000
1#
1"
#8100000
0"
#8130000
1"
#8160000
0"
#8190000
0#
1"
#8220000
0"
#8250000
1"
#8280000
0"
#8310000
1#
1"
#8340000
0"
#8370000
0#
1"
#8400000
0"
#8430000
1"
#8460000
0"
#8490000
1"
#8520000
0"
#8550000
1#
1"
#8580000
0"
#8610000
0#
1"
#8640000
0"
#8670000
1"
#8700000
0"
#8730000
1#
1"
#8760000
0"
#8790000
0#
1"
#8820000
0"
#8850000
1#
1"
#8880000
0"
#8910000
1"
#8940000
0"
#8970000
1"
#9000000
0"
#9030000
1"
#9060000
0"
#9090000
1"
#9120000
0"
#9150000
0#
1"
#9180000
0"
#9210000
1"
#9240000
0"
#9270000
1"
#9300000
0"
#9330000
1#
1"
#9360000
0"
#9390000
0#
1"
#9420000
0"
#9450000
1"
#9480000
0"
#9510000
1#
1"
#9540000
0"
#9570000
1"
#9600000
0"
#9630000
0#
1"
#9660000
0"
#9690000
1"
#9720000
0"
#9750000
1"
#9780000
0"
#9810000
1#
1"
#9840000
0"
#9870000
1"
#9900000
0"
#9930000
0#
1"
#9960000
0"
#9990000
1"
#10020000
0"
#10050000
1"
#10080000
0"
#10110000
1#
1"
#10140000
0"
#10170000
1"
#10200000
0"
#10230000
0#
1"
#10260000
0"
#10290000
1"
#10320000
0"
#10350000
1"
#10380000
0"
#10410000
1#
1"
#10440000
0"
#10470000
0#
1"
#10500000
0"
#10530000
1"
#10560000
0"
#10590000
1#
1"
#10620000
0"
#10650000
0#
1"
#10680000
0"
#10710000
1"
#10740000
0"
#10770000
1"
#10800000
0"
#10830000
1#
1"
#10860000
0"
#10890000
0#
1"
#10920000
0"
#10950000
1#
1"
#10980000
0"
#11010000
1"
#11040000
0"
#11070000
0#
1"
#11100000
0"
#11130000
1"
#11160000
0"
#11190000
1"
#11220000
0"
#11250000
1"
#11280000
0"
#11310000
1#
1"
#11340000
0"
#11370000
0#
1"
#11400000
0"
#11430000
1"
#11460000
0"
#11490000
1"
#11520000
0"
#11550000
1"
#11580000
0"
#11610000
1#
1"
#11640000
0"
#11670000
1"
#11700000
0"
#11730000
1"
#11760000
0"
#11790000
0#
1"
#11820000
0"
#11850000
1#
1"
#11880000
0"
#11910000
1"
#11940000
0"
#11970000
1"
#12000000
0"
#12030000
0#
1"
#12060000
0"
#12090000
1"
#12120000
0"
#12150000
1#
1"
#12180000
0"
#12210000
1"
#12240000
0"
#12270000
1"
#12300000
0"
#12330000
1"
#12360000
0"
#12390000
1"
#12420000
0"
#12450000
0#
1"
#12480000
0"
#12510000
1#
1"
#12540000
0"
#12570000
1"
#12600000
0"
#12630000
0#
1"
#12660000
0"
#12690000
1"
#12720000
0"
#12750000
1"
#12780000
0"
#12810000
1"
#12840000
0"
#12870000
1#
1"
#12900000
0"
#12930000
1"
#12960000
0"
#12990000
0#
1"
#13020000
0"
#13050000
1"
#13080000
0"
#13110000
1#
1"
#13140000
0"
#13170000
0#
1"
#13200000
0"
#13230000
1"
#13260000
0"
#13290000
1#
1"
#13320000
0"
#13350000
0#
1"
#13380000
0"
#13410000
1"
#13440000
0"
#13470000
1#
1"
#13500000
0"
#13530000
0#
1"
#13560000
0"
#13590000
1"
#13620000
0"
#13650000
1#
1"
#13680000
0"
#13710000
1"
#13740000
0"
#13770000
1"
#13800000
0"
#13830000
0#
1"
#13860000
0"
#13890000
1"
#13920000
0"
#13950000
1"
#13980000
0"
#14010000
1#
1"
#14040000
0"
#14070000
0#
1"
#14100000
0"
#14130000
1"
#14160000
0"
#14190000
1#
1"
#14220000
0"
#14250000
0#
1"
#14280000
0"
#14310000
1"
#14340000
0"
#14370000
1"
#14400000
0"
#14430000
1"
#14460000
0"
#14490000
1#
1"
#14520000
0"
#14550000
0#
1"
#14580000
0"
#14610000
1"
#14640000
0"
#14670000
1"
#14700000
0"
#14730000
1#
1"
#14760000
0"
#14790000
1"
#14820000
0"
#14850000
0#
1"
#14880000
0"
#14910000
1#
1"
#14940000
0"
#14970000
1"
#15000000
0"
#15030000
1"
#15060000
0"
#15090000
1"
#15120000
0"
#15150000
0#
1"
#15180000
0"
#15210000
1#
1"
#15240000
0"
#15270000
1"
#15300000
0"
#15330000
1"
#15360000
0"
#15390000
0#
1"
#15420000
0"
#15450000
1"
#15480000
0"
#15510000
1#
1"
#15540000
0"
#15570000
0#
1"
#15600000
0"
#15630000
1"
#15660000
0"
#15690000
1#
1"
#15720000
0"
#15750000
1"
#15780000
0"
#15810000
0#
1"
#15840000
0"
#15870000
1"
#15900000
0"
#15930000
1#
1"
#15960000
0"
#15990000
0#
1"
#16020000
0"
#16050000
1"
#16080000
0"
#16110000
1#
1"
#16140000
0"
#16170000
0#
1"
#16200000
0"
#16230000
1#
1"
#16260000
0"
#16290000
1"
#16320000
0"
#16350000
0#
1"
#16380000
0"
#16410000
1#
1"
#16440000
0"
#16470000
0#
1"
#16500000
0"
#16530000
1#
1"
#16560000
0"
#16590000
0#
1"
#16620000
0"
#16650000
1"
#16680000
0"
#16710000
1#
1"
#16740000
0"
#16770000
0#
1"
#16800000
0"
#16830000
1"
#16860000
0"
#16890000
1"
#16920000
0"
#16950000
1#
1"
#16980000
0"
#17010000
1"
#17040000
0"
#17070000
1"
#17100000
0"
#17130000
1"
#17160000
0"
#17190000
1"
#17220000
0"
#17250000
0#
1"
#17280000
0"
#17310000
1#
1"
#17340000
0"
#17370000
1"
#17400000
0"
#17430000
1"
#17460000
0"
#17490000
0#
1"
#17520000
0"
#17550000
1"
#17580000
0"
#17610000
1"
#17640000
0"
#17670000
1"
#17700000
0"
#17730000
1"
#17760000
0"
#17790000
1"
#17820000
0"
#17850000
1#
1"
#17880000
0"
#17910000
1"
#17940000
0"
#17970000
1"
#18000000
0"
#18030000
1"
#18060000
0"
#18090000
1"
#18120000
0"
#18150000
1"
#18180000
0"
#18210000
1"
#18240000
0"
#18270000
0#
1"
#18300000
0"
#18330000
1#
1"
#18360000
0"
#18390000
1"
#18420000
0"
#18450000
1"
#18480000
0"
#18510000
1"
#18540000
0"
#18570000
1"
#18600000
0"
#18630000
1"
#18660000
0"
#18690000
1"
#18720000
0"
#18750000
1"
#18780000
0"
#18810000
0#
1"
#18840000
0"
#18870000
1"
#18900000
0"
#18930000
1#
1"
#18960000
0"
#18990000
1"
#19020000
0"
#19050000
0#
1"
#19080000
0"
#19110000
1"
#19140000
0"
#19170000
1"
#19200000
0"
#19230000
1"
#19260000
0"
#19290000
1#
1"
#19320000
0"
#19350000
0#
1"
#19380000
0"
#19410000
1"
#19440000
0"
#19470000
1"
#19500000
0"
#19530000
1"
#19560000
0"
#19590000
1"
#19620000
0"
#19650000
1"
#19680000
0"
#19710000
1#
1"
#19740000
0"
#19770000
0#
1"
#19800000
0"
#19830000
1"
#19860000
0"
#19890000
1#
1"
#19920000
0"
#19950000
0#
1"
#19980000
0"
#20010000
1"
#20040000
0"
#20070000
1"
#20100000
0"
#20130000
1"
#20160000
0"
#20190000
1#
1"
#20220000
0"
#20250000
1"
#20280000
0"
#20310000
1"
#20340000
0"
#20370000
1"
#20400000
0"
#20430000
1"
#20460000
0"
#20490000
0#
1"
#20520000
0"
#20550000
1#
1"
#20580000
0"
#20610000
1"
#20640000
0"
#20670000
1"
#20700000
0"
#20730000
0#
1"
#20760000
0"
#20790000
1#
1"
#20820000
0"
#20850000
0#
1"
#20880000
0"
#20910000
1"
#20940000
0"
#20970000
1#
1"
#21000000
0"
#21030000
1"
#21060000
0"
#21090000
0#
1"
#21120000
0"
#21150000
1#
1"
#21180000
0"
#21210000
0#
1"
#21240000
0"
#21270000
1"
#21300000
0"
#21330000
1#
1"
#21360000
0"
#21390000
0#
1"
#21420000
0"
#21450000
1"
#21480000
0"
#21510000
1"
#21540000
0"
#21570000
1"
#21600000
0"
#21630000
1#
1"
#21660000
0"
#21690000
1"
#21720000
0"
#21750000
1"
#21780000
0"
#21810000
1"
#21840000
0"
#21870000
0#
1"
#21900000
0"
#21930000
1#
1"
#21960000
0"
#21990000
1"
#22020000
0"
#22050000
1"
#22080000
0"
#22110000
1"
#22140000
0"
#22170000
1"
#22200000
0"
#22230000
1"
#22260000
0"
#22290000
1"
#22320000
0"
#22350000
0#
1"
#22380000
0"
#22410000
1#
1"
#22440000
0"
#22470000
0#
1"
#22500000
0"
#22530000
1#
1"
#22560000
0"
#22590000
0#
1"
#22620000
0"
#22650000
1"
#22680000
0"
#22710000
1#
1"
#22740000
0"
#22770000
0#
1"
#22800000
0"
#22830000
1"
#22860000
0"
#22890000
1"
#22920000
0"
#22950000
1"
#22980000
0"
#23010000
1"
#23040000
0"
#23070000
1#
1"
#23100000
0"
#23130000
0#
1"
#23160000
0"
#23190000
1"
#23220000
0"
#23250000
1"
#23280000
0"
#23310000
1"
#23340000
0"
#23370000
1"
#23400000
0"
#23430000
1"
#23460000
0"
#23490000
1#
1"
#23520000
0"
#23550000
0#
1"
#23580000
0"
#23610000
1#
1"
#23640000
0"
#23670000
0#
1"
#23700000
0"
#23730000
1"
#23760000
0"
#23790000
1#
1"
#23820000
0"
#23850000
0#
1"
#23880000
0"
#23910000
1#
1"
#23940000
0"
#23970000
1"
#24000000
0"
#24030000
0#
1"
#24060000
0"
#24090000
1#
1"
#24120000
0"
#24150000
0#
1"
#24180000
0"
#24210000
1#
1"
#24240000
0"
#24270000
0#
1"
#24300000
0"
#24330000
1"
#24360000
0"
#24390000
1"
#24420000
0"
#24450000
1"
#24480000
0"
#24510000
1#
1"
#24540000
0"
#24570000
0#
1"
#24600000
0"
#24630000
1#
1"
#24660000
0"
#24690000
0#
1"
#24720000
0"
#24750000
1#
1"
#24780000
0"
#24810000
1"
#24840000
0"
#24870000
0#
1"
#24900000
0"
#24930000
1#
1"
#24960000
0"
#24990000
0#
1"
#25020000
0"
#25050000
1#
1"
#25080000
0"
#25110000
1"
#25140000
0"
#25170000
1"
#25200000
0"
#25230000
0#
1"
#25260000
0"
#25290000
1#
1"
#25320000
0"
#25350000
1"
#25380000
0"
#25410000
0#
1"
#25440000
0"
#25470000
1"
#25500000
0"
#25530000
1#
1"
#25560000
0"
#25590000
1"
#25620000
0"
#25650000
0#
1"
#25680000
0"
#25710000
1"
#25740000
0"
#25770000
1#
1"
#25800000
0"
#25830000
1"
#25860000
0"
#25890000
0#
1"
#25920000
0"
#25950000
1"
#25980000
0"
#26010000
1#
1"
#26040000
0"
#26070000
0#
1"
#26100000
0"
#26130000
1"
#26160000
0"
#26190000
1#
1"
#26220000
0"
#26250000
1"
#26280000
0"
#26310000
0#
1"
#26340000
0"
#26370000
1"
#26400000
0"
#26430000
1#
1"
#26460000
0"
#26490000
0#
1"
#26520000
0"
#26550000
1"
#26580000
0"
#26610000
1#
1"
#26640000
0"
#26670000
1"
#26700000
0"
#26730000
0#
1"
#26760000
0"
#26790000
1#
1"
#26820000
0"
#26850000
0#
1"
#26880000
0"
#26910000
1#
1"
#26940000
0"
#26970000
1"
#27000000
0"
#27030000
0#
1"
#27060000
0"
#27090000
1#
1"
#27120000
0"
#27150000
1"
#27180000
0"
#27210000
1"
#27240000
0"
#27270000
0#
1"
#27300000
0"
#27330000
1#
1"
#27360000
0"
#27390000
1"
#27420000
0"
#27450000
1"
#27480000
0"
#27510000
0#
1"
#27540000
0"
#27570000
1"
#27600000
0"
#27630000
1#
1"
#27660000
0"
#27690000
0#
1"
#27720000
0"
#27750000
1"
#27780000
0"
#27810000
1#
1"
#27840000
0"
#27870000
0#
1"
#27900000
0"
#27930000
1"
#27960000
0"
#27990000
1#
1"
#28020000
0"
#28050000
1"
#28080000
0"
#28110000
0#
1"
#28140000
0"
#28170000
1#
1"
#28200000
0"
#28230000
0#
1"
#28260000
0"
#28290000
1#
1"
#28320000
0"
#28350000
1"
#28380000
0"
#28410000
1"
#28440000
0"
#28470000
1"
#28500000
0"
#28530000
0#
1"
#28560000
0"
#28590000
1"
#28620000
0"
#28650000
1#
1"
#28680000
0"
#28710000
0#
1"
#28740000
0"
#28770000
1#
1"
#28800000
0"
#28830000
0#
1"
#28860000
0"
#28890000
1#
1"
#28920000
0"
#28950000
1"
#28980000
0"
#29010000
0#
1"
#29040000
0"
#29070000
1"
#29100000
0"
#29130000
1#
1"
#29160000
0"
#29190000
1"
#29220000
0"
#29250000
1"
#29280000
0"
#29310000
0#
1"
#29340000
0"
#29370000
1"
#29400000
0"
#29430000
1#
1"
#29460000
0"
#29490000
0#
1"
#29520000
0"
#29550000
1"
#29580000
0"
#29610000
1#
1"
#29640000
0"
#29670000
1"
#29700000
0"
#29730000
1"
#29760000
0"
#29790000
0#
1"
#29820000
0"
#29850000
1#
1"
#29880000
0"
#29910000
1"
#29940000
0"
#29970000
0#
1"
#30000000
0"
#30030000
1"
#30060000
0"
#30090000
1"
#30120000
0"
#30150000
1#
1"
#30180000
0"
#30210000
1"
#30240000
0"
#30270000
1"
#30300000
0"
#30330000
0#
1"
#30360000
0"
#30390000
1"
#30420000
0"
#30450000
1"
#30480000
0"
#30510000
1#
1"
#30540000
0"
#30570000
1"
#30600000
0"
#30630000
1"
#30660000
0"
#30690000
1"
#30720000
0"
#30750000
0#
1"
#30780000
0"
#30810000
1#
1"
#30840000
0"
#30870000
1"
#30900000
0"
#30930000
1"
#30960000
0"
#30990000
1"
#31020000
0"
#31050000
1"
#31080000
0"
#31110000
1"
#31140000
0"
#31170000
1"
#31200000
0"
#31230000
0#
1"
#31260000
0"
#31290000
1#
1"
#31320000
0"
#31350000
0#
1"
#31380000
0"
#31410000
1"
#31440000
0"
#31470000
1"
#31500000
0"
#31530000
1#
1"
#31560000
0"
#31590000
1"
#31620000
0"
#31650000
1"
#31680000
0"
#31710000
1"
#31740000
0"
#31770000
1"
#31800000
0"
#31830000
1"
#31860000
0"
#31890000
1"
#31920000
0"
#31950000
1"
#31980000
0"
#32010000
1"
#32040000
0"
#32070000
0#
1"
#32100000
0"
#32130000
1"
#32160000
0"
#32190000
1"
#32220000
0"
#32250000
1#
1"
#32280000
0"
#32310000
0#
1"
#32340000
0"
#32370000
1"
#32400000
0"
#32430000
1"
#32460000
0"
#32490000
1#
1"
#32520000
0"
#32550000
1"
#32580000
0"
#32610000
0#
1"
#32640000
0"
#32670000
1"
#32700000
0"
#32730000
1"
#32760000
0"
#32790000
1#
1"
#32820000
0"
#32850000
1"
#32880000
0"
#32910000
0#
1"
#32940000
0"
#32970000
1#
1"
#33000000
0"
#33030000
0#
1"
#33060000
0"
#33090000
1#
1"
#33120000
0"
#33150000
0#
1"
#33180000
0"
#33210000
1"
#33240000
0"
#33270000
1"
#33300000
0"
#33330000
1#
1"
#33360000
0"
#33390000
1"
#33420000
0"
#33450000
1"
#33480000
0"
#33510000
0#
1"
#33540000
0"
#33570000
1#
1"
#33600000
0"
#33630000
0#
1"
#33660000
0"
#33690000
1#
1"
#33720000
0"
#33750000
0#
1"
#33780000
0"
#33810000
1#
1"
#33840000
0"
#33870000
1"
#33900000
0"
#33930000
0#
1"
#33960000
0"
#33990000
1"
#34020000
0"
#34050000
1"
#34080000
0"
#34110000
1"
#34140000
0"
#34170000
1#
1"
#34200000
0"
#34230000
1"
#34260000
0"
#34290000
0#
1"
#34320000
0"
#34350000
1"
#34380000
0"
#34410000
1#
1"
#34440000
0"
#34470000
0#
1"
#34500000
0"
#34530000
1#
1"
#34560000
0"
#34590000
0#
1"
#34620000
0"
#34650000
1#
1"
#34680000
0"
#34710000
1"
#34740000
0"
#34770000
0#
1"
#34800000
0"
#34830000
1#
1"
#34860000
0"
#34890000
1"
#34920000
0"
#34950000
0#
1"
#34980000
0"
#35010000
1"
#35040000
0"
#35070000
1"
#35100000
0"
#35130000
1"
#35160000
0"
#35190000
1#
1"
#35220000
0"
#35250000
1"
#35280000
0"
#35310000
1"
#35340000
0"
#35370000
1"
#35400000
0"
#35430000
1"
#35460000
0"
#35490000
0#
1"
#35520000
0"
#35550000
1"
#35580000
0"
#35610000
1"
#35640000
0"
#35670000
1"
#35700000
0"
#35730000
1"
#35760000
0"
#35790000
1"
#35820000
0"
#35850000
1"
#35880000
0"
#35910000
1#
1"
#35940000
0"
#35970000
1"
#36000000
0"
#36030000
1"
#36060000
0"
#36090000
1"
#36120000
0"
#36150000
1"
#36180000
0"
#36210000
1"
#36240000
0"
#36270000
1"
#36300000
0"
#36330000
0#
1"
#36360000
0"
#36390000
1"
#36420000
0"
#36450000
1"
#36480000
0"
#36510000
1"
#36540000
0"
#36570000
1"
#36600000
0"
#36630000
1"
#36660000
0"
#36690000
1#
1"
#36720000
0"
#36750000
1"
#36780000
0"
#36810000
0#
1"
#36840000
0"
#36870000
1#
1"
#36900000
0"
#36930000
0#
1"
#36960000
0"
#36990000
1#
1"
#37020000
0"
#37050000
1"
#37080000
0"
#37110000
1"
#37140000
0"
#37170000
0#
1"
#37200000
0"
#37230000
1"
#37260000
0"
#37290000
1"
#37320000
0"
#37350000
1#
1"
#37380000
0"
#37410000
1"
#37440000
0"
#37470000
0#
1"
#37500000
0"
#37530000
1#
1"
#37560000
0"
#37590000
0#
1"
#37620000
0"
#37650000
1"
#37680000
0"
#37710000
1"
#37740000
0"
#37770000
1"
#37800000
0"
#37830000
1"
#37860000
0"
#37890000
1"
#37920000
0"
#37950000
1#
1"
#37980000
0"
#38010000
0#
1"
#38040000
0"
#38070000
1"
#38100000
0"
#38130000
1#
1"
#38160000
0"
#38190000
0#
1"
#38220000
0"
#38250000
1"
#38280000
0"
#38310000
1#
1"
#38340000
0"
#38370000
1"
#38400000
0"
#38430000
1"
#38460000
0"
#38490000
0#
1"
#38520000
0"
#38550000
1"
#38580000
0"
#38610000
1#
1"
#38640000
0"
#38670000
1"
#38700000
0"
#38730000
1"
#38760000
0"
#38790000
1"
#38820000
0"
#38850000
0#
1"
#38880000
0"
#38910000
1#
1"
#38940000
0"
#38970000
1"
#39000000
0"
#39030000
1"
#39060000
0"
#39090000
1"
#39120000
0"
#39150000
0#
1"
#39180000
0"
#39210000
1#
1"
#39240000
0"
#39270000
0#
1"
#39300000
0"
#39330000
1"
#39360000
0"
#39390000
1#
1"
#39420000
0"
#39450000
0#
1"
#39480000
0"
#39510000
1"
#39540000
0"
#39570000
1#
1"
#39600000
0"
#39630000
0#
1"
#39660000
0"
#39690000
1"
#39720000
0"
#39750000
1"
#39780000
0"
#39810000
1"
#39840000
0"
#39870000
1"
#39900000
0"
#39930000
1"
#39960000
0"
#39990000
1#
1"
#40020000
0"
#40050000
1"
#40080000
0"
#40110000
0#
1"
#40140000
0"
#40170000
1"
#40200000
0"
#40230000
1#
1"
#40260000
0"
#40290000
1"
#40320000
0"
#40350000
1"
#40380000
0"
#40410000
1"
#40440000
0"
#40470000
1"
#40500000
0"
#40530000
1"
#40560000
0"
#40590000
1"
#40620000
0"
#40650000
0#
1"
#40680000
0"
#40710000
1#
1"
#40740000
0"
#40770000
0#
1"
#40800000
0"
#40830000
1"
#40860000
0"
#40890000
1"
#40920000
0"
#40950000
1#
1"
#40980000
0"
#41010000
1"
#41040000
0"
#41070000
0#
1"
#41100000
0"
#41130000
1#
1"
#41160000
0"
#41190000
1"
#41220000
0"
#41250000
1"
#41280000
0"
#41310000
0#
1"
#41340000
0"
#41370000
1"
#41400000
0"
#41430000
1"
#41460000
0"
#41490000
1"
#41520000
0"
#41550000
1#
1"
#41580000
0"
#41610000
1"
#41640000
0"
#41670000
1"
#41700000
0"
#41730000
0#
1"
#41760000
0"
#41790000
1#
1"
#41820000
0"
#41850000
0#
1"
#41880000
0"
#41910000
1"
#41940000
0"
#41970000
1"
#42000000
0"
#42030000
1"
#42060000
0"
#42090000
1"
#42120000
0"
#42150000
1"
#42180000
0"
#42210000
1"
#42240000
0"
#42270000
1#
1"
#42300000
0"
#42330000
0#
1"
#42360000
0"
#42390000
1"
#42420000
0"
#42450000
1#
1"
#42480000
0"
#42510000
1"
#42540000
0"
#42570000
1"
#42600000
0"
#42630000
1"
#42660000
0"
#42690000
1"
#42720000
0"
#42750000
0#
1"
#42780000
0"
#42810000
1"
#42840000
0"
#42870000
1"
#42900000
0"
#42930000
1"
#42960000
0"
#42990000
1#
1"
#43020000
0"
#43050000
1"
#43080000
0"
#43110000
0#
1"
#43140000
0"
#43170000
1"
#43200000
0"
#43230000
1#
1"
#43260000
0"
#43290000
1"
#43320000
0"
#43350000
1"
#43380000
0"
#43410000
1"
#43440000
0"
#43470000
1"
#43500000
0"
#43530000
0#
1"
#43560000
0"
#43590000
1"
#43620000
0"
#43650000
1"
#43680000
0"
#43710000
1#
1"
#43740000
0"
#43770000
0#
1"
#43800000
0"
#43830000
1#
1"
#43860000
0"
#43890000
0#
1"
#43920000
0"
#43950000
1"
#43980000
0"
#44010000
1"
#44040000
0"
#44070000
1"
#44100000
0"
#44130000
1"
#44160000
0"
#44190000
1#
1"
#44220000
0"
#44250000
0#
1"
#44280000
0"
#44310000
1#
1"
#44340000
0"
#44370000
1"
#44400000
0"
#44430000
0#
1"
#44460000
0"
#44490000
1#
1"
#44520000
0"
#44550000
1"
#44580000
0"
#44610000
0#
1"
#44640000
0"
#44670000
1#
1"
#44700000
0"
#44730000
0#
1"
#44760000
0"
#44790000
1#
1"
#44820000
0"
#44850000
1"
#44880000
0"
#44910000
0#
1"
#44940000
0"
#44970000
1"
#45000000
0"
#45030000
1#
1"
#45060000
0"
#45090000
1"
#45120000
0"
#45150000
0#
1"
#45180000
0"
#45210000
1"
#45240000
0"
#45270000
1"
#45300000
0"
#45330000
1"
#45360000
0"
#45390000
1#
1"
#45420000
0"
#45450000
1"
#45480000
0"
#45510000
1"
#45540000
0"
#45570000
0#
1"
#45600000
0"
#45630000
1"
#45660000
0"
#45690000
1#
1"
#45720000
0"
#45750000
1"
#45780000
0"
#45810000
1"
#45840000
0"
#45870000
1"
#45900000
0"
#45930000
0#
1"
#45960000
0"
#45990000
1"
#46020000
0"
#46050000
1#
1"
#46080000
0"
#46110000
1"
#46140000
0"
#46170000
0#
1"
#46200000
0"
#46230000
1"
#46260000
0"
#46290000
1#
1"
#46320000
0"
#46350000
0#
1"
#46380000
0"
#46410000
1#
1"
#46440000
0"
#46470000
0#
1"
#46500000
0"
#46530000
1#
1"
#46560000
0"
#46590000
1"
#46620000
0"
#46650000
0#
1"
#46680000
0"
#46710000
1"
#46740000
0"
#46770000
1"
#46800000
0"
#46830000
1"
#46860000
0"
#46890000
1"
#46920000
0"
#46950000
1#
1"
#46980000
0"
#47010000
0#
1"
#47040000
0"
#47070000
1#
1"
#47100000
0"
#47130000
0#
1"
#47160000
0"
#47190000
1"
#47220000
0"
#47250000
1"
#47280000
0"
#47310000
1#
1"
#47340000
0"
#47370000
0#
1"
#47400000
0"
#47430000
1"
#47460000
0"
#47490000
1#
1"
#47520000
0"
#47550000
0#
1"
#47580000
0"
#47610000
1#
1"
#47640000
0"
#47670000
1"
#47700000
0"
#47730000
1"
#47760000
0"
#47790000
1"
#47820000
0"
#47850000
1"
#47880000
0"
#47910000
0#
1"
#47940000
0"
#47970000
1#
1"
#48000000
0"
#48030000
1"
#48060000
0"
#48090000
0#
1"
#48120000
0"
#48150000
1"
#48180000
0"
#48210000
1#
1"
#48240000
0"
#48270000
0#
1"
#48300000
0"
#48330000
1#
1"
#48360000
0"
#48390000
1"
#48420000
0"
#48450000
1"
#48480000
0"
#48510000
1"
#48540000
0"
#48570000
1"
#48600000
0"
#48630000
0#
1"
#48660000
0"
#48690000
1#
1"
#48720000
0"
#48750000
0#
1"
#48780000
0"
#48810000
1#
1"
