PartA4/stoplight2_testb.v
`timescale 1 ns / 1ps
module stoplight2_testb;
	reg PED, CLK;
	stoplight2 x1(PED,CLK,G,Y,R);
	initial begin
		x1.S0 = 0;
		x1.S1 = 0;
		x1.S2 = 0;
		x1.S3 = 0;
		x1.S4 = 0;
		CLK = 0;
		PED = 0;
		$dumpfile("stoplight2_testb.vcd");
		$dumpvars(0,stoplight2_testb);
		#1500000 $finish; // this is to check when clock go over 1M 
	end

	always #30 CLK=~CLK; // increasing clock speed so the program reaches 1M faster

	always @(posedge CLK) begin
		if ($time <= 1000000) begin
			if ({x1.S4,x1.S3,x1.S2,x1.S1,x1.S0} == 4'b01000) begin
				$display("%8d", $time," state:",x1.S4,x1.S3,x1.S2,x1.S1,x1.S0, "  (reached target)"); 
				$display("The number of clock cycles until reachable: ","%8d", $time);
				$finish; 
			end
			else begin
				$display("%8d", $time, " state:", x1.S4,x1.S3,x1.S2,x1.S1,x1.S0);
			end
			PED = $random;
		end
		else begin
		$display("Timed out, unreachable for state 01000");
		$finish; 
		end
	end
endmodule

module stoplight2(Ped,clock,SigG,SigY,SigR);
input Ped,clock;
reg S4,S3,S2,S1,S0;
output SigG,SigY,SigR;
wire n15,n16,n17,n18,n19,n20,n21,n22,n23,n24,n25,n26,n27,n28,n29,n30,n31,n32,n33,n34,n35,n36,n37,n38,n39,n40,n41,n42,n43,n44,n45,n46,n47,n48,n49,n50,n51,n52,n53,n54,n55,n57,n58,n60,n61,n62,n63,n64,n65,n67,n68,n69,n70,n71,n72,n73,n74,n75,n77,n78,n79,n80,n81,n82,n83,n84,n85,n86,n88,n89,n90,n91,n92,n93,n94,n95,n96,n97,n99,n100,n101,n102,n103,n104,n105,n106,n107,n108,n109,n110,n111,n112,n113,n114,n116,n117,n118,n119,n120,NS4,NS3,NS2,NS1,NS0;
not g0(n15,S0);
not g1(n16,S4);
not g2(n17,S3);
and g3(n18,n17,n16);
and g4(n19,n18,S2);
and g5(n20,n19,n15);
not g6(n21,n20);
not g7(n22,S1);
not g8(n23,Ped);
and g9(n24,n23,n22);
and g10(n25,n24,n19);
not g11(n26,n25);
and g12(n27,Ped,S0);
and g13(n28,n27,n19);
not g14(n29,n28);
and g15(n30,n29,n26);
and g16(n31,n30,n21);
not g17(n32,S2);
and g18(n33,n18,n32);
and g19(n34,S0,S1);
and g20(n35,n34,Ped);
and g21(n36,n35,n33);
not g22(n37,n36);
and g23(n38,n32,n17);
and g24(n39,n34,n23);
and g25(n40,n39,n38);
not g26(n41,n40);
and g27(n42,n41,n37);
and g28(n43,S2,n17);
and g29(n44,n43,n39);
not g30(n45,n44);
and g31(n46,n32,S4);
and g32(n47,n15,n22);
and g33(n48,n47,n46);
not g34(n49,n48);
and g35(n50,n17,S4);
not g36(n51,n50);
and g37(n52,n51,n49);
and g38(n53,n52,n45);
and g39(n54,n53,n42);
and g40(n55,n54,n31);
not g41(SigG,n55);
and g42(n57,S3,n16);
and g43(n58,n22,n32);
and g44(SigY,n58,n57);
and g45(n60,S0,n22);
and g46(n61,n60,n33);
not g47(n62,n61);
and g48(n63,n33,n15);
not g49(n64,n63);
and g50(n65,n64,n62);
not g51(SigR,n65);
and g52(n67,Ped,n15);
and g53(n68,n67,n50);
not g54(n69,n68);
and g55(n70,S0,S4);
and g56(n71,n70,n23);
not g57(n72,n71);
and g58(n73,n72,n69);
and g59(n74,n73,n45);
and g60(n75,n74,n29);
not g61(NS4,n75);
and g62(n77,S1,S2);
and g63(n78,n77,n71);
not g64(n79,n78);
and g65(n80,n57,n15);
not g66(n81,n80);
and g67(n82,n15,S3);
and g68(n83,n82,Ped);
not g69(n84,n83);
and g70(n85,n84,n81);
and g71(n86,n85,n79);
not g72(NS3,n86);
and g73(n88,n22,S2);
and g74(n89,n23,S0);
and g75(n90,n89,n88);
not g76(n91,n90);
and g77(n92,n15,S2);
and g78(n93,n92,Ped);
not g79(n94,n93);
and g80(n95,n94,n91);
and g81(n96,n95,n21);
and g82(n97,n96,n42);
not g83(NS2,n97);
and g84(n99,n70,n24);
not g85(n100,n99);
and g86(n101,S2,n16);
and g87(n102,n101,n67);
not g88(n103,n102);
and g89(n104,n103,n100);
and g90(n105,n15,S1);
and g91(n106,n105,Ped);
not g92(n107,n106);
and g93(n108,S1,n16);
and g94(n109,n108,n15);
not g95(n110,n109);
and g96(n111,n110,n107);
and g97(n112,n111,n104);
and g98(n113,n62,n37);
and g99(n114,n113,n112);
not g100(NS1,n114);
and g101(n116,n81,n69);
and g102(n117,n110,n94);
and g103(n118,n117,n116);
and g104(n119,n64,n26);
and g105(n120,n119,n118);
not g106(NS0,n120);
always @(posedge clock) begin
S4<=NS4;
S3<=NS3;
S2<=NS2;
S1<=NS1;
S0<=NS0;
end
endmodule
//State:01000

PartA4/stoplight2_testb.vcd
$date
	Tue Mar 09 22:40:49 2021
$end
$version
	Icarus Verilog
$end
$timescale
	1ps
$end
$scope module stoplight2_testb $end
$var wire 1 ! Y $end
$var wire 1 " R $end
$var wire 1 # G $end
$var reg 1 $ CLK $end
$var reg 1 % PED $end
$scope module x1 $end
$var wire 1 & NS0 $end
$var wire 1 ' NS1 $end
$var wire 1 ( NS2 $end
$var wire 1 ) NS3 $end
$var wire 1 * NS4 $end
$var wire 1 % Ped $end
$var wire 1 # SigG $end
$var wire 1 " SigR $end
$var wire 1 ! SigY $end
$var wire 1 $ clock $end
$var wire 1 + n100 $end
$var wire 1 , n101 $end
$var wire 1 - n102 $end
$var wire 1 . n103 $end
$var wire 1 / n104 $end
$var wire 1 0 n105 $end
$var wire 1 1 n106 $end
$var wire 1 2 n107 $end
$var wire 1 3 n108 $end
$var wire 1 4 n109 $end
$var wire 1 5 n110 $end
$var wire 1 6 n111 $end
$var wire 1 7 n112 $end
$var wire 1 8 n113 $end
$var wire 1 9 n114 $end
$var wire 1 : n116 $end
$var wire 1 ; n117 $end
$var wire 1 < n118 $end
$var wire 1 = n119 $end
$var wire 1 > n120 $end
$var wire 1 ? n15 $end
$var wire 1 @ n16 $end
$var wire 1 A n17 $end
$var wire 1 B n18 $end
$var wire 1 C n19 $end
$var wire 1 D n20 $end
$var wire 1 E n21 $end
$var wire 1 F n22 $end
$var wire 1 G n23 $end
$var wire 1 H n24 $end
$var wire 1 I n25 $end
$var wire 1 J n26 $end
$var wire 1 K n27 $end
$var wire 1 L n28 $end
$var wire 1 M n29 $end
$var wire 1 N n30 $end
$var wire 1 O n31 $end
$var wire 1 P n32 $end
$var wire 1 Q n33 $end
$var wire 1 R n34 $end
$var wire 1 S n35 $end
$var wire 1 T n36 $end
$var wire 1 U n37 $end
$var wire 1 V n38 $end
$var wire 1 W n39 $end
$var wire 1 X n40 $end
$var wire 1 Y n41 $end
$var wire 1 Z n42 $end
$var wire 1 [ n43 $end
$var wire 1 \ n44 $end
$var wire 1 ] n45 $end
$var wire 1 ^ n46 $end
$var wire 1 _ n47 $end
$var wire 1 ` n48 $end
$var wire 1 a n49 $end
$var wire 1 b n50 $end
$var wire 1 c n51 $end
$var wire 1 d n52 $end
$var wire 1 e n53 $end
$var wire 1 f n54 $end
$var wire 1 g n55 $end
$var wire 1 h n57 $end
$var wire 1 i n58 $end
$var wire 1 j n60 $end
$var wire 1 k n61 $end
$var wire 1 l n62 $end
$var wire 1 m n63 $end
$var wire 1 n n64 $end
$var wire 1 o n65 $end
$var wire 1 p n67 $end
$var wire 1 q n68 $end
$var wire 1 r n69 $end
$var wire 1 s n70 $end
$var wire 1 t n71 $end
$var wire 1 u n72 $end
$var wire 1 v n73 $end
$var wire 1 w n74 $end
$var wire 1 x n75 $end
$var wire 1 y n77 $end
$var wire 1 z n78 $end
$var wire 1 { n79 $end
$var wire 1 | n80 $end
$var wire 1 } n81 $end
$var wire 1 ~ n82 $end
$var wire 1 !" n83 $end
$var wire 1 "" n84 $end
$var wire 1 #" n85 $end
$var wire 1 $" n86 $end
$var wire 1 %" n88 $end
$var wire 1 &" n89 $end
$var wire 1 '" n90 $end
$var wire 1 (" n91 $end
$var wire 1 )" n92 $end
$var wire 1 *" n93 $end
$var wire 1 +" n94 $end
$var wire 1 ," n95 $end
$var wire 1 -" n96 $end
$var wire 1 ." n97 $end
$var wire 1 /" n99 $end
$var reg 1 0" S0 $end
$var reg 1 1" S1 $end
$var reg 1 2" S2 $end
$var reg 1 3" S3 $end
$var reg 1 4" S4 $end
$upscope $end
$upscope $end
$enddefinitions $end
#0
$dumpvars
04"
03"
02"
01"
00"
0/"
1."
1-"
1,"
1+"
0*"
0)"
1("
0'"
0&"
0%"
1$"
1#"
1""
0!"
0~
1}
0|
1{
0z
0y
1x
1w
1v
1u
0t
0s
1r
0q
0p
0o
0n
1m
1l
0k
0j
1i
0h
1g
1f
1e
1d
1c
0b
1a
0`
1_
0^
1]
0\
0[
1Z
1Y
0X
0W
1V
1U
0T
0S
0R
1Q
1P
1O
1N
1M
0L
0K
1J
0I
1H
1G
1F
1E
0D
0C
1B
1A
1@
1?
0>
0=
1<
1;
1:
19
18
17
16
15
04
03
12
01
00
1/
1.
0-
0,
1+
0*
0)
0(
0'
1&
0%
0$
0#
1"
0!
$end
#30000
1'
0&
09
1>
08
1=
0l
1n
1k
0_
0m
1&"
1j
0?
10"
1$
#60000
0$
#90000
1&
0>
07
0<
18
0=
02
06
0;
1l
0n
11
05
0k
1m
1p
10
14
0i
0j
1?
13
0F
00"
11"
0H
0&"
0G
0K
1%
1$
#120000
0$
#150000
1#
0g
1(
0f
0."
0&
17
0Z
08
0"
1>
16
1<
0U
1o
1=
12
1;
1T
1n
01
15
1S
0m
0p
00
04
1R
1K
0?
10"
1$
#180000
0$
#210000
1&
0>
1f
0/
0,"
07
0<
1Z
18
0.
0+"
02
06
0;
1U
0O
0-"
1-
1*"
11
05
0T
0E
0S
1p
1)"
10
14
0Q
0V
1D
0R
0K
1?
1,
1y
1[
0P
1C
00"
12"
1$
#240000
0$
#270000
0(
0&
0'
1."
1>
19
1#
1-"
1<
17
1*
0g
1/
1,"
1;
16
0N
0x
0O
1.
1+"
12
0M
1E
0-
0*"
01
15
1S
1L
0D
0p
0)"
00
04
1R
1K
0?
10"
1$
#300000
0$
#330000
1&
0>
0w
0<
0v
0:
1O
1*
0f
0r
0a
1N
0x
0e
1q
1`
1M
0d
1p
0S
1_
1V
1^
1i
0L
0c
0B
0K
1?
03
0R
1F
0,
0y
0[
1P
0C
1b
0@
00"
01"
02"
14"
1$
#360000
0$
#390000
0*
0&
1x
1>
1w
1<
1v
1:
1a
1r
0`
0q
0_
0p
1s
1j
1K
0?
10"
1$
#420000
0$
#450000
1&
0#
1"
0>
1g
0o
0=
1f
0n
1e
1m
1d
1Q
1_
1c
1B
0j
1?
0s
0b
0^
1@
00"
04"
0'
19
0*
17
1x
1/
1w
1+
1v
0/"
1u
1H
0t
0&"
1G
0K
0%
1$
#480000
0$
#510000
1'
0&
09
1>
08
1=
0l
1n
1k
0_
0m
1j
1K
0?
10"
0H
0G
0p
1%
1$
#540000
0$
#570000
1&
0>
07
0<
18
0=
02
06
0;
1l
0n
11
05
0k
1m
1p
10
14
0i
0j
0K
1?
13
0F
00"
11"
1$
#600000
0$
#630000
1#
0g
1(
0'
0f
0."
0&
19
0Z
0"
1>
17
1<
0Y
1o
1=
16
1;
1X
1n
15
1W
0m
00
04
1&"
1R
0?
10"
12
1G
0p
01
0%
1$
#660000
0$
#690000
1&
0>
07
0<
1f
0/
0,"
0;
1Z
0.
0+"
0O
0-"
1-
1*"
0E
1p
1)"
1_
1%"
0Q
0V
1D
1?
03
0R
1F
1,
1[
0P
1C
00"
01"
12"
1'
09
1Y
18
0X
1U
0W
0&"
0T
0G
0K
0S
1%
1$
#720000
0$
#750000
0(
0&
0'
1."
1>
19
1#
1-"
1<
17
1*
0g
1/
1,"
1;
0N
0x
0O
1.
1+"
16
0M
1E
0-
0*"
12
1L
0D
0p
0)"
01
1S
0_
0%"
1K
0?
13
00
1y
1R
0F
10"
11"
1$
#780000
0$
#810000
0a
1`
0d
1H
1_
1V
1^
1i
0c
0B
1?
03
0R
1F
0,
0y
0[
1P
0C
1b
0@
00"
01"
02"
14"
1#
0f
0g
0e
1w
1O
0*
1]
1N
1x
0\
1M
0W
0&"
0L
1G
0K
0S
0%
1$
#840000
0$
#870000
0#
1"
1g
0o
0=
1f
0n
1e
1m
1d
1a
1Q
1c
0`
1B
0b
0^
1@
04"
0*
1&
1x
0>
1w
1<
1v
1:
1r
0H
0q
0G
1p
1%
1$
#900000
0$
#930000
1'
0&
09
1>
08
1=
0l
1n
1k
0_
0m
1&"
1j
0?
10"
1H
1G
0p
0%
1$
#960000
0$
#990000
1&
0>
07
0<
18
0=
02
06
0;
1l
0n
11
05
0k
1m
1p
10
14
0i
0j
1?
13
0F
00"
11"
0H
0&"
0G
0K
1%
1$
#1020000
0$
#1050000
1#
0g
1(
0'
0f
0."
0&
19
0Z
0"
1>
17
1<
0Y
1o
1=
16
1;
1X
1n
15
1W
0m
00
04
1&"
1R
0?
10"
12
1G
0p
01
0%
1$
#1080000
0$
#1110000
1&
0>
07
0<
1f
0/
0,"
0;
1Z
0.
0+"
0O
0-"
1-
1*"
0E
1p
1)"
1_
1%"
0Q
0V
1D
1?
03
0R
1F
1,
1[
0P
1C
00"
01"
12"
1'
09
1Y
18
0X
1U
0W
0&"
0T
0G
0K
0S
1%
1$
#1140000
0$
#1170000
0(
0&
0'
1."
1>
19
1#
1-"
1<
17
1*
0g
1/
1,"
1;
0N
0x
0O
1.
1+"
16
0M
1E
0-
0*"
12
1L
0D
0p
0)"
01
1S
0_
0%"
1K
0?
13
00
1y
1R
0F
10"
11"
1$
#1200000
0$
#1230000
0a
1`
0d
1H
1_
1V
1^
1i
0c
0B
1?
03
0R
1F
0,
0y
0[
1P
0C
1b
0@
00"
01"
02"
14"
1#
0f
0g
0e
1w
1O
0*
1]
1N
1x
0\
1M
0W
0&"
0L
1G
0K
0S
0%
1$
#1260000
0$
#1290000
0#
1"
1g
0o
0=
1f
0n
1e
1m
1d
1a
1Q
1c
0`
1B
0b
0^
1@
04"
0*
1&
1x
0>
1w
1<
1v
1:
1r
0H
0q
0G
1p
1%
1$
#1320000
0$
#1350000
1'
0&
09
1>
08
1=
0l
1n
1k
0_
0m
1&"
1j
0?
10"
1H
1G
0p
0%
1$
#1380000
0$
#1410000
1&
0>
07
0<
18
0=
06
0;
1l
0n
05
0k
1m
10
14
0H
0i
0&"
0j
1?
13
0F
00"
11"
1$
#1440000
0$
#1470000
1#
0g
1(
0'
0f
0."
0&
19
0Z
0"
1>
17
1<
0Y
1o
1=
16
1;
1X
1n
15
1W
0m
00
04
1&"
1R
0?
10"
1$
#1500000
0$
#1530000
1&
0>
07
0<
1f
0/
0,"
0;
1Z
0.
0+"
0O
0-"
1-
1*"
0E
1p
1)"
1_
1%"
0Q
0V
1D
1?
03
0R
1F
1,
1[
0P
1C
00"
01"
12"
1'
09
1Y
18
0X
1U
0W
0&"
0T
0G
0K
0S
1%
1$
#1560000
0$
#1590000
1*
0(
0f
0x
1O
1."
0e
0w
1-"
0]
1E
1\
0D
0)"
1W
0_
0%"
1&"
0?
13
00
1y
1R
0F
10"
11"
0'
19
0&
1N
1=
17
1>
1J
1/
1<
0I
1.
1,"
1;
0H
0-
1+"
1G
0p
0*"
0%
1$
#1620000
0$
#1650000
1&
0>
0<
0v
0:
1*
0r
0a
0x
1q
1`
0d
1p
1_
1V
1^
1i
0c
0B
1?
03
0R
1F
0,
0y
0[
1P
0C
1b
0@
00"
01"
02"
14"
0f
0e
0w
1O
1]
1N
0\
1M
0W
0&"
0L
0G
0K
0S
1%
1$
#1680000
0$
#1710000
0*
0&
1x
1>
1w
1<
1v
1:
1a
1r
0`
0q
0_
0p
1s
1j
1K
0?
10"
1$
#1740000
0$
#1770000
1&
0#
1"
0>
1g
0o
0=
1f
0n
1e
1m
1d
1Q
1_
1p
1c
1B
0j
0K
1?
0s
0b
0^
1@
00"
04"
1$
#1800000
0$
#1830000
1'
0&
09
1>
08
1=
0l
1n
1k
0_
0m
0p
1j
1K
0?
10"
1$
#1860000
0$
#1890000
1&
0>
07
0<
18
0=
06
0;
1l
0n
05
0k
1m
10
14
0i
0j
1?
13
0F
00"
11"
0H
0&"
1G
0K
0%
1$
#1920000
0$
#1950000
1#
0g
1(
0'
0f
0."
0&
19
0Z
0"
1>
17
1<
0Y
1o
1=
16
1;
1X
1n
15
1W
0m
00
04
1&"
1R
0?
10"
1$
#1980000
0$
#2010000
1&
1f
0>
0*
0N
0=
1x
1Z
0J
1e
1w
1Y
0O
0-"
1I
1]
0X
0E
1)"
0W
1H
1_
1%"
0\
0Q
0V
1D
0&"
1?
03
0R
1F
1,
1[
0P
1C
00"
01"
12"
1$
#2040000
0$
#2070000
1(
0."
0,"
0-"
0("
1E
1'"
0D
0_
0)"
1&"
1j
0?
10"
1$
#2100000
0$
#2130000
0(
0&
1."
1>
1-"
1=
1,"
1*
1J
1("
0x
0I
0'"
0M
0H
0&"
1L
0G
1K
1%
1$
#2160000
0$
#2190000
0f
0a
0e
1`
0d
1_
1V
1^
1i
0c
0B
0j
1?
0,
0%"
0[
1P
0C
1b
0@
00"
02"
14"
0(
0&
1."
1#
1>
1-"
0g
1=
1,"
1O
0*
1J
1("
1N
1x
0I
0'"
1M
1H
0&"
0L
1G
0K
0%
1$
#2220000
0$
#2250000
0#
1"
1g
0o
0=
1f
0n
1e
1m
1d
1a
1Q
1c
0`
1B
0b
0^
1@
04"
0*
1&
1x
0>
1w
1<
1v
1:
1r
0H
0q
0G
1p
1%
1$
#2280000
0$
#2310000
1'
0&
09
1>
08
1=
0l
1n
1k
0_
0m
0p
1j
1K
0?
10"
1$
#2340000
0$
#2370000
1&
0>
07
0<
18
0=
02
06
0;
1l
0n
11
05
0k
1m
1p
10
14
0i
0j
0K
1?
13
0F
00"
11"
1$
#2400000
0$
#2430000
1#
0g
1(
0f
0."
0&
17
0Z
08
0"
1>
16
1<
0U
1o
1=
12
1;
1T
1n
01
15
1S
0m
0p
00
04
1R
1K
0?
10"
1$
#2460000
0$
#2490000
1&
0>
1f
0/
0,"
07
0<
1Z
18
0.
0+"
02
06
0;
1U
0O
0-"
1-
1*"
11
05
0T
0E
0S
1p
1)"
10
14
0Q
0V
1D
0R
0K
1?
1,
1y
1[
0P
1C
00"
12"
1$
#2520000
0$
#2550000
1*
0'
0&
0f
0x
1#
0(
19
1>
0e
0w
0g
1."
17
1<
0]
1O
1-"
16
1;
1\
1E
15
1W
0D
0)"
00
04
1&"
1R
0?
10"
1/
1.
1,"
0-
1+"
12
1G
0p
0*"
01
0%
1$
#2580000
0$
#2610000
0*
1x
1w
0a
1]
1`
0d
0W
1H
1_
0\
1V
1^
1i
0c
0B
0&"
1?
03
0R
1F
0,
0y
0[
1P
0C
1b
0@
00"
01"
02"
14"
1$
#2640000
0$
#2670000
0#
1"
1g
0o
0=
1f
0n
1e
1m
1d
1a
1Q
1c
0`
1B
0b
0^
1@
04"
0*
1&
1x
0>
1w
1<
1v
1:
1r
0H
0q
0G
1p
1%
1$
#2700000
0$
#2730000
1'
0&
09
1>
08
1=
0l
1n
1k
0_
0m
0p
1j
1K
0?
10"
1$
#2760000
0$
#2790000
1&
0>
07
0<
18
0=
02
06
0;
1l
0n
11
05
0k
1m
1p
10
14
0i
0j
0K
1?
13
0F
00"
11"
1$
#2820000
0$
#2850000
1#
0g
1(
0'
0f
0."
0&
19
0Z
0"
1>
17
1<
0Y
1o
1=
16
1;
1X
1n
15
1W
0m
00
04
1&"
1R
0?
10"
12
1G
0p
01
0%
1$
#2880000
0$
#2910000
1&
1f
0>
0*
0N
0=
1x
1Z
0J
1e
1w
1Y
0O
0-"
1I
1]
0X
0E
1)"
0W
1H
1_
1%"
0\
0Q
0V
1D
0&"
1?
03
0R
1F
1,
1[
0P
1C
00"
01"
12"
1$
#2940000
0$
#2970000
1(
0."
0,"
0-"
0("
1E
1'"
0D
0_
0)"
1&"
1j
0?
10"
1$
#3000000
0$
#3030000
1$
#3060000
0$
#3090000
1$
#3120000
0$
#3150000
0(
0&
1."
1>
1-"
1=
1,"
1*
1J
1("
0x
0I
0'"
0M
0H
0&"
1L
0G
1K
1%
1$
#3180000
0$
#3210000
0f
0a
0e
1`
0d
1_
1V
1^
1i
0c
0B
0j
1?
0,
0%"
0[
1P
0C
1b
0@
00"
02"
14"
0(
0&
1."
1#
1>
1-"
0g
1=
1,"
1O
0*
1J
1("
1N
1x
0I
0'"
1M
1H
0&"
0L
1G
0K
0%
1$
#3240000
0$
#3270000
1&
0#
1"
0>
1g
0o
0=
1f
0n
1e
1m
1d
1a
1Q
1c
0`
1B
0b
0^
1@
04"
1$
#3300000
0$
#3330000
1'
0&
09
1>
08
1=
0l
1n
1k
0_
0m
1j
1K
0?
10"
0H
0G
0p
1%
1$
#3360000
0$
#3390000
1&
0>
07
0<
18
0=
02
06
0;
1l
0n
11
05
0k
1m
1p
10
14
0i
0j
0K
1?
13
0F
00"
11"
1$
#3420000
0$
#3450000
1#
0g
1(
0'
0f
0."
0&
19
0Z
0"
1>
17
1<
0Y
1o
1=
16
1;
1X
1n
15
1W
0m
00
04
1&"
1R
0?
10"
12
1G
0p
01
0%
1$
#3480000
0$
#3510000
1&
1f
0>
0*
0N
0=
1x
1Z
0J
1e
1w
1Y
0O
0-"
1I
1]
0X
0E
1)"
0W
1H
1_
1%"
0\
0Q
0V
1D
0&"
1?
03
0R
1F
1,
1[
0P
1C
00"
01"
12"
1$
#3540000
0$
#3570000
1(
0."
0,"
0-"
0("
1E
1'"
0D
0_
0)"
1&"
1j
0?
10"
1$
#3600000
0$
#3630000
1$
#3660000
0$
#3690000
1$
#3720000
0$
#3750000
0(
0&
1."
1>
1-"
1=
1,"
1*
1J
1("
0x
0I
0'"
0M
0H
0&"
1L
0G
1K
1%
1$
#3780000
0$
#3810000
1&
0>
0w
0<
0v
0:
1O
1*
0f
0r
0a
1N
0x
0e
1q
1`
1M
0d
1_
1p
1V
1^
1i
0L
0c
0B
0j
0K
1?
0,
0%"
0[
1P
0C
1b
0@
00"
02"
14"
1$
#3840000
0$
#3870000
0*
0&
1x
1>
1w
1<
1v
1:
1a
1r
0`
0q
0_
0p
1s
1j
1K
0?
10"
1$
#3900000
0$
#3930000
1&
0#
1"
0>
1g
0o
0=
1f
0n
1e
1m
1d
1Q
1_
1p
1c
1B
0j
0K
1?
0s
0b
0^
1@
00"
04"
1$
#3960000
0$
#3990000
1'
0&
09
1>
08
1=
0l
1n
1k
0_
0m
0p
1j
1K
0?
10"
1$
#4020000
0$
#4050000
1&
0>
07
0<
18
0=
06
0;
1l
0n
05
0k
1m
10
14
0i
0j
1?
13
0F
00"
11"
0H
0&"
1G
0K
0%
1$
#4080000
0$
#4110000
1#
0g
1(
0'
0f
0."
0&
19
0Z
0"
1>
17
1<
0Y
1o
1=
16
1;
1X
1n
15
1W
0m
00
04
1&"
1R
0?
10"
1$
#4140000
0$
#4170000
1&
0>
07
0<
1f
0/
0,"
0;
1Z
0.
0+"
0O
0-"
1-
1*"
0E
1p
1)"
1_
1%"
0Q
0V
1D
1?
03
0R
1F
1,
1[
0P
1C
00"
01"
12"
1'
09
1Y
18
0X
1U
0W
0&"
0T
0G
0K
0S
1%
1$
#4200000
0$
#4230000
0(
0&
0'
1."
1>
19
1#
1-"
1<
17
1*
0g
1/
1,"
1;
0N
0x
0O
1.
1+"
16
0M
1E
0-
0*"
12
1L
0D
0p
0)"
01
1S
0_
0%"
1K
0?
13
00
1y
1R
0F
10"
11"
1$
#4260000
0$
#4290000
1&
0>
0w
0<
0v
0:
1O
1*
0f
0r
0a
1N
0x
0e
1q
1`
1M
0d
1p
0S
1_
1V
1^
1i
0L
0c
0B
0K
1?
03
0R
1F
0,
0y
0[
1P
0C
1b
0@
00"
01"
02"
14"
1$
#4320000
0$
#4350000
1'
09
07
0/
1a
0u
0+
0`
1t
1/"
0_
1&"
1s
1j
0?
10"
1*
0&
0x
1>
0w
1<
0v
1:
1r
1H
0q
1G
0p
0%
1$
#4380000
0$
#4410000
0*
0'
1x
19
1w
17
1v
1/
1u
1+
0t
0/"
10
0H
0i
0&"
0s
0j
1?
0F
00"
11"
1$
#4440000
0$
#4470000
0#
1"
1g
0o
0=
1f
0n
1e
1m
1d
1Q
1_
1i
1c
1B
00
1F
0b
0^
1@
01"
04"
0*
1&
1x
0>
0'
1w
1<
19
1v
1:
17
1r
16
0q
12
0G
1p
01
1%
1$
#4500000
0$
#4530000
1'
0&
09
1>
08
1=
0l
1n
1k
0_
0m
0p
1j
1K
0?
10"
1$
#4560000
0$
#4590000
1&
0>
07
0<
18
0=
06
0;
1l
0n
05
0k
1m
10
14
0i
0j
1?
13
0F
00"
11"
0H
0&"
1G
0K
0%
1$
#4620000
0$
#4650000
1#
0g
1(
0f
0."
0&
17
0Z
08
0"
1>
16
1<
0U
1o
1=
1;
1T
1n
15
1S
0m
00
04
1R
1K
0?
10"
12
0G
0p
01
1%
1$
#4680000
0$
#4710000
1&
0>
1f
0/
0,"
07
0<
1Z
18
0.
0+"
02
06
0;
1U
0O
0-"
1-
1*"
11
05
0T
0E
0S
1p
1)"
10
14
0Q
0V
1D
0R
0K
1?
1,
1y
1[
0P
1C
00"
12"
1$
#4740000
0$
#4770000
1*
0'
0&
0f
0x
1#
0(
19
1>
0e
0w
0g
1."
17
1<
0]
1O
1-"
16
1;
1\
1E
15
1W
0D
0)"
00
04
1&"
1R
0?
10"
1/
1.
1,"
0-
1+"
12
1G
0p
0*"
01
0%
1$
#4800000
0$
#4830000
1&
0>
0<
0v
0:
1*
0r
0a
0x
1q
1`
0d
1p
1_
1V
1^
1i
0c
0B
1?
03
0R
1F
0,
0y
0[
1P
0C
1b
0@
00"
01"
02"
14"
0f
0e
0w
1O
1]
1N
0\
1M
0W
0&"
0L
0G
0K
0S
1%
1$
#4860000
0$
#4890000
0*
0&
1x
1>
1w
1<
1v
1:
1a
1r
0`
0q
0_
0p
1s
1j
1K
0?
10"
1$
#4920000
0$
#4950000
1&
0#
1"
0>
1g
0o
0=
1f
0n
1e
1m
1d
1Q
1_
1p
1c
1B
0j
0K
1?
0s
0b
0^
1@
00"
04"
1$
#4980000
0$
#5010000
1'
0&
09
1>
08
1=
0l
1n
1k
0_
0m
1&"
1j
0?
10"
1H
1G
0p
0%
1$
#5040000
0$
#5070000
1&
0>
07
0<
18
0=
02
06
0;
1l
0n
11
05
0k
1m
1p
10
14
0i
0j
1?
13
0F
00"
11"
0H
0&"
0G
0K
1%
1$
#5100000
0$
#5130000
1#
0g
1(
0f
0."
0&
17
0Z
08
0"
1>
16
1<
0U
1o
1=
12
1;
1T
1n
01
15
1S
0m
0p
00
04
1R
1K
0?
10"
1$
#5160000
0$
#5190000
1&
0>
0*
07
0<
1x
06
0;
1e
1w
0O
0-"
05
1]
0E
1)"
10
14
0\
0Q
0V
1D
0R
1?
1,
1y
1[
0P
1C
00"
12"
1#
0g
1(
1'
1f
0."
09
1Y
1Z
18
0X
1U
0W
0&"
0T
1G
0K
0S
0%
1$
#5220000
0$
#5250000
1*
0'
0&
0f
0x
1#
0(
19
1>
0e
0w
0g
1."
17
1<
0]
1O
1-"
16
1;
1\
1E
15
1W
0D
0)"
00
04
1&"
1R
0?
10"
1$
#5280000
0$
#5310000
0*
1x
1w
0a
1]
1`
0d
0W
1H
1_
0\
1V
1^
1i
0c
0B
0&"
1?
03
0R
1F
0,
0y
0[
1P
0C
1b
0@
00"
01"
02"
14"
1$
#5340000
0$
#5370000
1&
0#
1"
0>
1g
0o
0=
1f
0n
1e
1m
1d
1a
1Q
1c
0`
1B
0b
0^
1@
04"
1$
#5400000
0$
#5430000
1'
0&
09
1>
08
1=
0l
1n
1k
0_
0m
1j
1K
0?
10"
0H
0G
0p
1%
1$
#5460000
0$
#5490000
1&
0>
07
0<
18
0=
02
06
0;
1l
0n
11
05
0k
1m
1p
10
14
0i
0j
0K
1?
13
0F
00"
11"
1$
#5520000
0$
#5550000
1#
0g
1(
0'
0f
0."
0&
19
0Z
0"
1>
17
1<
0Y
1o
1=
16
1;
1X
1n
15
1W
0m
00
04
1&"
1R
0?
10"
12
1G
0p
01
0%
1$
#5580000
0$
#5610000
1&
1f
0>
0*
0N
0=
1x
1Z
0J
1e
1w
1Y
0O
0-"
1I
1]
0X
0E
1)"
0W
1H
1_
1%"
0\
0Q
0V
1D
0&"
1?
03
0R
1F
1,
1[
0P
1C
00"
01"
12"
1$
#5640000
0$
#5670000
0(
0&
1."
1>
1#
1-"
1*
0g
0x
0O
0M
1E
1L
0D
0_
0)"
1j
1K
0?
10"
0'
19
0N
1=
17
1J
1/
1<
0I
1.
1,"
1;
0H
0-
1+"
0G
0p
0*"
1%
1$
#5700000
0$
#5730000
1&
0>
0w
0<
0v
0:
1O
1*
0f
0r
0a
1N
0x
0e
1q
1`
1M
0d
1_
1p
1V
1^
1i
0L
0c
0B
0j
0K
1?
0,
0%"
0[
1P
0C
1b
0@
00"
02"
14"
1$
#5760000
0$
#5790000
0*
0&
1x
1>
1w
1<
1v
1:
1a
1r
0`
0q
0_
0p
1s
1j
1K
0?
10"
1$
#5820000
0$
#5850000
1&
0#
1"
0>
1g
0o
0=
1f
0n
1e
1m
1d
1Q
1_
1p
1c
1B
0j
0K
1?
0s
0b
0^
1@
00"
04"
1$
#5880000
0$
#5910000
1'
0&
09
1>
08
1=
0l
1n
1k
0_
0m
0p
1j
1K
0?
10"
1$
#5940000
0$
#5970000
1&
0>
07
0<
18
0=
06
0;
1l
0n
05
0k
1m
10
14
0i
0j
1?
13
0F
00"
11"
0H
0&"
1G
0K
0%
1$
#6000000
0$
