PartA4/stoplight1_testb.v
`timescale 1 ns / 1ps
module stoplight1_testb;
	reg PED, CLK;
	stoplight x1(PED,CLK,G,Y,R);
	initial begin
		x1.S0 = 0;
		x1.S1 = 0;
		x1.S2 = 0;
		x1.S3 = 0;
		CLK = 0;
		PED = 0;
		$dumpfile("stoplight1_testb.vcd");
		$dumpvars(0,stoplight1_testb);
		#1500000 $finish; // this is to check when clock go over 1M 
	end

	always #30 CLK=~CLK; // increasing clock speed so the program reaches 1M faster

	always @(posedge CLK) begin
		if ($time <= 1000000) begin
			if ({x1.S3,x1.S2,x1.S1,x1.S0} == 3'b0100) begin
				$display("%8d", $time," state:",x1.S3,x1.S2,x1.S1,x1.S0, "  (reached target)"); 
				$display("The number of clock cycles until reachable: ","%8d", $time);
				$finish; 
			end
			else begin
				$display("%8d", $time, " state:", x1.S3,x1.S2,x1.S1,x1.S0);
			end
			PED = $random;
		end
		else begin
		$display("Timed out, unreachable for state 0100");
		$finish; 
		end
	end
endmodule



module stoplight(Ped,clock,SigG,SigY,SigR);
input Ped,clock;
output SigG,SigY,SigR;
reg S3,S2,S1,S0;
wire n13,n14,n15,n16,n17,n18,n19,n20,n21,n22,n23,n24,n25,n26,n27,n28,n29,n30,n31,n32,n33,n34,n35,n36,n38,n39,n40,n42,n41,n43,n44,n45,n47,n48,n49,n50,n52,n53,n54,n55,n56,n57,n58,n59,n60,n61,n62,n64,n65,n66,n67,NS0,NS1,NS2,NS3;
not g0(n13,S3);
and g1(n14,S2,n13);
and g2(n15,Ped,S0);
and g3(n16,n15,n14);
not g4(n17,n16);
and g5(n18,S0,S1);
and g6(n19,n18,n14);
not g7(n20,n19);
and g8(n21,n20,n17);
not g9(n22,S0);
and g10(n23,n14,n22);
not g11(n24,n23);
not g12(n25,S2);
and g13(n26,n25,n13);
and g14(n27,n26,n18);
not g15(n28,n27);
not g16(n29,S1);
not g17(n30,Ped);
and g18(n31,n30,n29);
and g19(n32,n31,n14);
not g20(n33,n32);
and g21(n34,n33,n28);
and g22(n35,n34,n24);
and g23(n36,n35,n21);
not g24(SigG,n36);
and g25(n38,n25,S3);
and g26(SigY,n38,n29);
and g27(n40,S0,n29);
and g28(n41,n40,n26);
not g29(n42,n41);
and g30(n43,n26,n22);
not g31(n44,n43);
and g32(n45,n44,n42);
not g33(SigR,n45);
and g34(n47,n22,S3);
not g35(n48,n47);
and g36(n49,n48,n21);
not g37(NS3,n49);
not g38(NS2,n35);
and g39(n52,n22,S1);
not g40(n53,n52);
and g41(n54,n53,n42);
and g42(n55,S1,n25);
and g43(n56,n55,Ped);
not g44(n57,n56);
and g45(n58,n22,S2);
and g46(n59,n58,Ped);
not g47(n60,n59);
and g48(n61,n60,n57);
and g49(n62,n61,n54);
not g50(NS1,n62);
and g51(n64,n53,n48);
and g52(n65,n64,n33);
and g53(n66,n60,n44);
and g54(n67,n66,n65);
not g55(NS0,n67);
always @(posedge clock) begin
S3<=NS3;
S2<=NS2;
S1<=NS1;
S0<=NS0;
end
endmodule
//State:0100

PartA4/stoplight1_testb.vcd
$date
	Tue Mar 09 16:37:54 2021
$end
$version
	Icarus Verilog
$end
$timescale
	1ps
$end
$scope module stoplight1_testb $end
$var wire 1 ! Y $end
$var wire 1 " R $end
$var wire 1 # G $end
$var reg 1 $ CLK $end
$var reg 1 % PED $end
$scope module x1 $end
$var wire 1 & NS0 $end
$var wire 1 ' NS1 $end
$var wire 1 ( NS2 $end
$var wire 1 ) NS3 $end
$var wire 1 $ Ped $end
$var wire 1 # SigG $end
$var wire 1 " SigR $end
$var wire 1 ! SigY $end
$var wire 1 % clock $end
$var wire 1 * n13 $end
$var wire 1 + n14 $end
$var wire 1 , n15 $end
$var wire 1 - n16 $end
$var wire 1 . n17 $end
$var wire 1 / n18 $end
$var wire 1 0 n19 $end
$var wire 1 1 n20 $end
$var wire 1 2 n21 $end
$var wire 1 3 n22 $end
$var wire 1 4 n23 $end
$var wire 1 5 n24 $end
$var wire 1 6 n25 $end
$var wire 1 7 n26 $end
$var wire 1 8 n27 $end
$var wire 1 9 n28 $end
$var wire 1 : n29 $end
$var wire 1 ; n30 $end
$var wire 1 < n31 $end
$var wire 1 = n32 $end
$var wire 1 > n33 $end
$var wire 1 ? n34 $end
$var wire 1 @ n35 $end
$var wire 1 A n36 $end
$var wire 1 B n38 $end
$var wire 1 C n40 $end
$var wire 1 D n41 $end
$var wire 1 E n42 $end
$var wire 1 F n43 $end
$var wire 1 G n44 $end
$var wire 1 H n45 $end
$var wire 1 I n47 $end
$var wire 1 J n48 $end
$var wire 1 K n49 $end
$var wire 1 L n52 $end
$var wire 1 M n53 $end
$var wire 1 N n54 $end
$var wire 1 O n55 $end
$var wire 1 P n56 $end
$var wire 1 Q n57 $end
$var wire 1 R n58 $end
$var wire 1 S n59 $end
$var wire 1 T n60 $end
$var wire 1 U n61 $end
$var wire 1 V n62 $end
$var wire 1 W n64 $end
$var wire 1 X n65 $end
$var wire 1 Y n66 $end
$var wire 1 Z n67 $end
$var reg 1 [ S0 $end
$var reg 1 \ S1 $end
$var reg 1 ] S2 $end
$var reg 1 ^ S3 $end
$upscope $end
$upscope $end
$enddefinitions $end
#0
$dumpvars
0^
0]
0\
0[
0Z
0Y
1X
1W
1V
1U
1T
0S
0R
1Q
0P
0O
1N
1M
0L
1K
1J
0I
0H
0G
1F
1E
0D
0C
0B
1A
1@
1?
1>
0=
1<
1;
1:
19
08
17
16
15
04
13
12
11
00
0/
1.
0-
0,
0+
1*
0)
0(
0'
1&
0%
0$
0#
1"
0!
$end
#30000
0<
0;
1$
#60000
1<
1;
0$
#90000
1'
0&
0V
1Z
0N
1Y
0E
1G
1D
0F
1C
03
1,
1[
0<
0;
1%
1$
#120000
1<
0,
1;
0$
#150000
0<
1,
0;
1$
#180000
1<
0,
1;
0$
#210000
0<
1,
0;
1$
#240000
1<
0,
1;
0$
#270000
0<
1,
0;
1$
#300000
1<
0,
1;
0$
#330000
0<
1,
0;
1$
#360000
1<
0,
1;
0$
#390000
0<
1,
0;
1$
#420000
1<
0,
1;
0$
#450000
0<
1,
0;
0%
1$
#480000
1<
0,
1;
0$
#510000
1&
0Z
0X
0Y
0W
0U
1E
0G
0M
0Q
0D
1F
1L
1P
0C
13
1O
0:
0[
1\
0<
0,
0;
1%
1$
#540000
1U
1Q
1;
0P
0$
#570000
0U
0Q
0;
1P
1$
#600000
1U
1Q
1;
0P
0$
#630000
0U
0Q
0;
1P
0%
1$
#660000
1U
1Q
1;
0P
0$
#690000
1#
0&
0A
1(
0"
1Z
1X
0@
1H
1Y
1N
1W
0?
1G
1M
09
0F
0L
18
03
1/
1,
1[
0U
0Q
0;
1P
1%
1$
#720000
0'
1V
1U
1Q
0,
1;
0P
0$
#750000
1'
0V
0U
0Q
1,
0;
1P
1$
#780000
0'
1V
1U
1Q
0,
1;
0P
0$
#810000
1'
0V
0U
0Q
1,
0;
1P
0%
1$
#840000
0'
1V
1U
1Q
0,
1;
0P
0$
#870000
1&
0Z
0Y
0T
1?
1S
19
05
1R
08
07
14
13
0O
1:
0/
06
1+
0[
0\
1]
1'
0V
0U
1Q
0,
0;
0P
1%
1$
#900000
0?
0X
0'
1&
0>
1V
0Z
1=
1U
1Y
1<
1T
1;
0S
0$
#930000
1?
1X
1'
1>
0V
0=
0U
0Y
0<
0T
0;
1S
0%
1$
#960000
0?
0X
0'
1&
0>
1V
0Z
1=
1U
1Y
1<
1T
1;
0S
0$
#990000
0&
1Z
1)
0(
0K
1@
02
15
0.
04
0R
1-
1C
03
1,
1[
1?
1X
0'
1>
1V
0=
1U
1Y
0<
1T
0;
0S
1%
1$
#1020000
1(
1&
1#
0)
0@
0Z
0A
1K
0?
0X
12
0>
1.
1=
0-
1<
0,
1;
0$
#1050000
0(
0&
1)
1@
1Z
0K
1?
1X
02
1>
0.
0=
1-
0<
1,
0;
0%
1$
#1080000
1(
1&
1#
0)
0@
0Z
0A
1K
0?
0X
12
0>
1.
1=
0-
1<
0,
1;
0$
#1110000
0(
0&
1)
1@
1Z
0K
1?
1X
02
1>
0.
0=
1-
0<
1,
0;
1%
1$
#1140000
1(
1&
1#
0)
0@
0Z
0A
1K
0?
0X
12
0>
1.
1=
0-
1<
0,
1;
0$
#1170000
0(
0&
1)
1@
1Z
0K
1?
1X
02
1>
0.
0=
1-
0<
1,
0;
1$
#1200000
1(
1&
1#
0)
0@
0Z
0A
1K
0?
0X
12
0>
1.
1=
0-
1<
0,
1;
0$
#1230000
0(
0&
1)
1@
1Z
0K
1?
1X
02
1>
0.
0=
1-
0<
1,
0;
0%
1$
#1260000
1(
1&
1#
0)
0@
0Z
0A
1K
0?
0X
12
0>
1.
1=
0-
1<
0,
1;
0$
#1290000
0(
0&
1)
1@
1Z
0K
1?
1X
02
1>
0.
0=
1-
0<
1,
0;
1%
1$
#1320000
1(
1&
1#
0)
0@
0Z
0A
1K
0?
0X
12
0>
1.
1=
0-
1<
0,
1;
0$
#1350000
0(
0&
1)
1@
1Z
0K
1?
1X
02
1>
0.
0=
1-
0<
1,
0;
0%
1$
#1380000
1(
1&
1#
0)
0@
0Z
0A
1K
0?
0X
12
0>
1.
1=
0-
1<
0,
1;
0$
#1410000
0(
0&
1)
1@
1Z
0K
1?
1X
02
1>
0.
0=
1-
0<
1,
0;
1$
#1440000
1(
1&
1#
0)
0@
0Z
0A
1K
0?
0X
12
0>
1.
1=
0-
1<
0,
1;
0$
#1470000
0(
0&
1)
1@
1Z
0K
1?
1X
02
1>
0.
0=
1-
0<
1,
0;
1$
#1500000
1(
1&
1#
0)
0@
0Z
0A
1K
0?
0X
12
0>
1.
1=
0-
1<
0,
1;
0$
#1530000
0(
0&
1)
1@
1Z
0K
1?
1X
02
1>
0.
0=
1-
0<
1,
0;
1%
1$
#1560000
1(
1&
1#
0)
0@
0Z
0A
1K
0?
0X
12
0>
1.
1=
0-
1<
0,
1;
0$
#1590000
0(
0&
1)
1@
1Z
0K
1?
1X
02
1>
0.
0=
1-
0<
1,
0;
0%
1$
#1620000
1(
1&
1#
0)
0@
0Z
0A
1K
0?
0X
12
0>
1.
1=
0-
1<
0,
1;
0$
#1650000
0(
0&
1)
1@
1Z
0K
1?
1X
02
1>
0.
0=
1-
0<
1,
0;
1%
1$
#1680000
1(
1&
1#
0)
0@
0Z
0A
1K
0?
0X
12
0>
1.
1=
0-
1<
0,
1;
0$
#1710000
0(
0&
1)
1@
1Z
0K
1?
1X
02
1>
0.
0=
1-
0<
1,
0;
1$
#1740000
1(
1&
1#
0)
0@
0Z
0A
1K
0?
0X
12
0>
1.
1=
0-
1<
0,
1;
0$
#1770000
0(
0&
1)
1@
1Z
0K
1?
1X
02
1>
0.
0=
1-
0<
1,
0;
1$
#1800000
1(
1&
1#
0)
0@
0Z
0A
1K
0?
0X
12
0>
1.
1=
0-
1<
0,
1;
0$
#1830000
0(
0&
1)
1@
1Z
0K
1?
1X
02
1>
0.
0=
1-
0<
1,
0;
1$
#1860000
1(
1&
1#
0)
0@
0Z
0A
1K
0?
0X
12
0>
1.
1=
0-
1<
0,
1;
0$
#1890000
0(
0&
1)
1@
1Z
0K
1?
1X
02
1>
0.
0=
1-
0<
1,
0;
0%
1$
#1920000
1(
1&
1#
0)
0@
0Z
0A
1K
0?
0X
12
0>
1.
1=
0-
1<
0,
1;
0$
#1950000
0(
0&
1)
1@
1Z
0K
1?
1X
02
1>
0.
0=
1-
0<
1,
0;
1$
#1980000
1(
1&
1#
0)
0@
0Z
0A
1K
0?
0X
12
0>
1.
1=
0-
1<
0,
1;
0$
#2010000
0(
0&
1)
1@
1Z
0K
1?
1X
02
1>
0.
0=
1-
0<
1,
0;
1$
#2040000
1(
1&
1#
0)
0@
0Z
0A
1K
0?
0X
12
0>
1.
1=
0-
1<
0,
1;
0$
#2070000
0(
0&
1)
1@
1Z
0K
1?
1X
02
1>
0.
0=
1-
0<
1,
0;
1$
#2100000
1(
1&
1#
0)
0@
0Z
0A
1K
0?
0X
12
0>
1.
1=
0-
1<
0,
1;
0$
#2130000
0(
0&
1)
1@
1Z
0K
1?
1X
02
1>
0.
0=
1-
0<
1,
0;
1%
1$
#2160000
1(
1&
1#
0)
0@
0Z
0A
1K
0?
0X
12
0>
1.
1=
0-
1<
0,
1;
0$
#2190000
0(
0&
1)
1@
1Z
0K
1?
1X
02
1>
0.
0=
1-
0<
1,
0;
0%
1$
#2220000
1(
1&
1#
0)
0@
0Z
0A
1K
0?
0X
12
0>
1.
1=
0-
1<
0,
1;
0$
#2250000
0(
0&
1)
1@
1Z
0K
1?
1X
02
1>
0.
0=
1-
0<
1,
0;
1%
1$
#2280000
1(
1&
1#
0)
0@
0Z
0A
1K
0?
0X
12
0>
1.
1=
0-
1<
0,
1;
0$
#2310000
0(
0&
1)
1@
1Z
0K
1?
1X
02
1>
0.
0=
1-
0<
1,
0;
1$
#2340000
1(
1&
1#
0)
0@
0Z
0A
1K
0?
0X
12
0>
1.
1=
0-
1<
0,
1;
0$
#2370000
0(
0&
1)
1@
1Z
0K
1?
1X
02
1>
0.
0=
1-
0<
1,
0;
1$
#2400000
1(
1&
1#
0)
0@
0Z
0A
1K
0?
0X
12
0>
1.
1=
0-
1<
0,
1;
0$
#2430000
0(
0&
1)
1@
1Z
0K
1?
1X
02
1>
0.
0=
1-
0<
1,
0;
1$
#2460000
1(
1&
1#
0)
0@
0Z
0A
1K
0?
0X
12
0>
1.
1=
0-
1<
0,
1;
0$
#2490000
0(
0&
1)
1@
1Z
0K
1?
1X
02
1>
0.
0=
1-
0<
1,
0;
1$
#2520000
1(
1&
1#
0)
0@
0Z
0A
1K
0?
0X
12
0>
1.
1=
0-
1<
0,
1;
0$
#2550000
0(
0&
1)
1@
1Z
0K
1?
1X
02
1>
0.
0=
1-
0<
1,
0;
0%
1$
#2580000
1(
1&
1#
0)
0@
0Z
0A
1K
0?
0X
12
0>
1.
1=
0-
1<
0,
1;
0$
#2610000
0(
0&
1)
1@
1Z
0K
1?
1X
02
1>
0.
0=
1-
0<
1,
0;
1$
#2640000
1(
1&
1#
0)
0@
0Z
0A
1K
0?
0X
12
0>
1.
1=
0-
1<
0,
1;
0$
#2670000
0(
0&
1)
1@
1Z
0K
1?
1X
02
1>
0.
0=
1-
0<
1,
0;
1%
1$
#2700000
1(
1&
1#
0)
0@
0Z
0A
1K
0?
0X
12
0>
1.
1=
0-
1<
0,
1;
0$
#2730000
0(
0&
1)
1@
1Z
0K
1?
1X
02
1>
0.
0=
1-
0<
1,
0;
1$
#2760000
1(
1&
1#
0)
0@
0Z
0A
1K
0?
0X
12
0>
1.
1=
0-
1<
0,
1;
0$
#2790000
0(
0&
1)
1@
1Z
0K
1?
1X
02
1>
0.
0=
1-
0<
1,
0;
1$
#2820000
1(
1&
1#
0)
0@
0Z
0A
1K
0?
0X
12
0>
1.
1=
0-
1<
0,
1;
0$
#2850000
0(
0&
1)
1@
1Z
0K
1?
1X
02
1>
0.
0=
1-
0<
1,
0;
0%
1$
#2880000
1(
1&
1#
0)
0@
0Z
0A
1K
0?
0X
12
0>
1.
1=
0-
1<
0,
1;
0$
#2910000
0(
0&
1)
1@
1Z
0K
1?
1X
02
1>
0.
0=
1-
0<
1,
0;
1$
#2940000
1(
1&
1#
0)
0@
0Z
0A
1K
0?
0X
12
0>
1.
1=
0-
1<
0,
1;
0$
#2970000
0(
0&
1)
1@
1Z
0K
1?
1X
02
1>
0.
0=
1-
0<
1,
0;
1$
#3000000
1(
1&
1#
0)
0@
0Z
0A
1K
0?
0X
12
0>
1.
1=
0-
1<
0,
1;
0$
#3030000
0(
0&
1)
1@
1Z
0K
1?
1X
02
1>
0.
0=
1-
0<
1,
0;
1$
#3060000
1(
1&
1#
0)
0@
0Z
0A
1K
0?
0X
12
0>
1.
1=
0-
1<
0,
1;
0$
#3090000
0(
0&
1)
1@
1Z
0K
1?
1X
02
1>
0.
0=
1-
0<
1,
0;
1$
#3120000
1(
1&
1#
0)
0@
0Z
0A
1K
0?
0X
12
0>
1.
1=
0-
1<
0,
1;
0$
#3150000
0(
0&
1)
1@
1Z
0K
1?
1X
02
1>
0.
0=
1-
0<
1,
0;
1%
1$
#3180000
1(
1&
1#
0)
0@
0Z
0A
1K
0?
0X
12
0>
1.
1=
0-
1<
0,
1;
0$
#3210000
0(
0&
1)
1@
1Z
0K
1?
1X
02
1>
0.
0=
1-
0<
1,
0;
0%
1$
#3240000
1(
1&
1#
0)
0@
0Z
0A
1K
0?
0X
12
0>
1.
1=
0-
1<
0,
1;
0$
#3270000
0(
0&
1)
1@
1Z
0K
1?
1X
02
1>
0.
0=
1-
0<
1,
0;
1$
#3300000
1(
1&
1#
0)
0@
0Z
0A
1K
0?
0X
12
0>
1.
1=
0-
1<
0,
1;
0$
#3330000
0(
0&
1)
1@
1Z
0K
1?
1X
02
1>
0.
0=
1-
0<
1,
0;
1%
1$
#3360000
1(
1&
1#
0)
0@
0Z
0A
1K
0?
0X
12
0>
1.
1=
0-
1<
0,
1;
0$
#3390000
0(
0&
1)
1@
1Z
0K
1?
1X
02
1>
0.
0=
1-
0<
1,
0;
1$
#3420000
1(
1&
1#
0)
0@
0Z
0A
1K
0?
0X
12
0>
1.
1=
0-
1<
0,
1;
0$
#3450000
0(
0&
1)
1@
1Z
0K
1?
1X
02
1>
0.
0=
1-
0<
1,
0;
0%
1$
#3480000
1(
1&
1#
0)
0@
0Z
0A
1K
0?
0X
12
0>
1.
1=
0-
1<
0,
1;
0$
#3510000
0(
0&
1)
1@
1Z
0K
1?
1X
02
1>
0.
0=
1-
0<
1,
0;
1$
#3540000
1(
1&
1#
0)
0@
0Z
0A
1K
0?
0X
12
0>
1.
1=
0-
1<
0,
1;
0$
#3570000
0(
0&
1)
1@
1Z
0K
1?
1X
02
1>
0.
0=
1-
0<
1,
0;
1$
#3600000
1(
1&
1#
0)
0@
0Z
0A
1K
0?
0X
12
0>
1.
1=
0-
1<
0,
1;
0$
#3630000
0(
0&
1)
1@
1Z
0K
1?
1X
02
1>
0.
0=
1-
0<
1,
0;
1$
#3660000
1(
1&
1#
0)
0@
0Z
0A
1K
0?
0X
12
0>
1.
1=
0-
1<
0,
1;
0$
#3690000
0(
0&
1)
1@
1Z
0K
1?
1X
02
1>
0.
0=
1-
0<
1,
0;
1$
#3720000
1(
1&
1#
0)
0@
0Z
0A
1K
0?
0X
12
0>
1.
1=
0-
1<
0,
1;
0$
#3750000
0(
0&
1)
1@
1Z
0K
1?
1X
02
1>
0.
0=
1-
0<
1,
0;
1%
1$
#3780000
1(
1&
1#
0)
0@
0Z
0A
1K
0?
0X
12
0>
1.
1=
0-
1<
0,
1;
0$
#3810000
0(
0&
1)
1@
1Z
0K
1?
1X
02
1>
0.
0=
1-
0<
1,
0;
1$
#3840000
1(
1&
1#
0)
0@
0Z
0A
1K
0?
0X
12
0>
1.
1=
0-
1<
0,
1;
0$
#3870000
0(
0&
1)
1@
1Z
0K
1?
1X
02
1>
0.
0=
1-
0<
1,
0;
1$
#3900000
1(
1&
1#
0)
0@
0Z
0A
1K
0?
0X
12
0>
1.
1=
0-
1<
0,
1;
0$
#3930000
0(
0&
1)
1@
1Z
0K
1?
1X
02
1>
0.
0=
1-
0<
1,
0;
1$
#3960000
1(
1&
1#
0)
0@
0Z
0A
1K
0?
0X
12
0>
1.
1=
0-
1<
0,
1;
0$
#3990000
0(
0&
1)
1@
1Z
0K
1?
1X
02
1>
0.
0=
1-
0<
1,
0;
1$
#4020000
1(
1&
1#
0)
0@
0Z
0A
1K
0?
0X
12
0>
1.
1=
0-
1<
0,
1;
0$
#4050000
0(
0&
1)
1@
1Z
0K
1?
1X
02
1>
0.
0=
1-
0<
1,
0;
0%
1$
#4080000
1(
1&
1#
0)
0@
0Z
0A
1K
0?
0X
12
0>
1.
1=
0-
1<
0,
1;
0$
#4110000
0(
0&
1)
1@
1Z
0K
1?
1X
02
1>
0.
0=
1-
0<
1,
0;
1$
#4140000
1(
1&
1#
0)
0@
0Z
0A
1K
0?
0X
12
0>
1.
1=
0-
1<
0,
1;
0$
#4170000
0(
0&
1)
1@
1Z
0K
1?
1X
02
1>
0.
0=
1-
0<
1,
0;
1%
1$
#4200000
1(
1&
1#
0)
0@
0Z
0A
1K
0?
0X
12
0>
1.
1=
0-
1<
0,
1;
0$
#4230000
0(
0&
1)
1@
1Z
0K
1?
1X
02
1>
0.
0=
1-
0<
1,
0;
1$
#4260000
1(
1&
1#
0)
0@
0Z
0A
1K
0?
0X
12
0>
1.
1=
0-
1<
0,
1;
0$
#4290000
0(
0&
1)
1@
1Z
0K
1?
1X
02
1>
0.
0=
1-
0<
1,
0;
1$
#4320000
1(
1&
1#
0)
0@
0Z
0A
1K
0?
0X
12
0>
1.
1=
0-
1<
0,
1;
0$
#4350000
0(
0&
1)
1@
1Z
0K
1?
1X
02
1>
0.
0=
1-
0<
1,
0;
0%
1$
#4380000
1(
1&
1#
0)
0@
0Z
0A
1K
0?
0X
12
0>
1.
1=
0-
1<
0,
1;
0$
#4410000
0(
0&
1)
1@
1Z
0K
1?
1X
02
1>
0.
0=
1-
0<
1,
0;
1$
#4440000
1(
1&
1#
0)
0@
0Z
0A
1K
0?
0X
12
0>
1.
1=
0-
1<
0,
1;
0$
#4470000
0(
0&
1)
1@
1Z
0K
1?
1X
02
1>
0.
0=
1-
0<
1,
0;
1%
1$
#4500000
1(
1&
1#
0)
0@
0Z
0A
1K
0?
0X
12
0>
1.
1=
0-
1<
0,
1;
0$
#4530000
0(
0&
1)
1@
1Z
0K
1?
1X
02
1>
0.
0=
1-
0<
1,
0;
1$
#4560000
1(
1&
1#
0)
0@
0Z
0A
1K
0?
0X
12
0>
1.
1=
0-
1<
0,
1;
0$
#4590000
0(
0&
1)
1@
1Z
0K
1?
1X
02
1>
0.
0=
1-
0<
1,
0;
0%
1$
#4620000
1(
1&
1#
0)
0@
0Z
0A
1K
0?
0X
12
0>
1.
1=
0-
1<
0,
1;
0$
#4650000
0(
0&
1)
1@
1Z
0K
1?
1X
02
1>
0.
0=
1-
0<
1,
0;
1%
1$
#4680000
1(
1&
1#
0)
0@
0Z
0A
1K
0?
0X
12
0>
1.
1=
0-
1<
0,
1;
0$
#4710000
0(
0&
1)
1@
1Z
0K
1?
1X
02
1>
0.
0=
1-
0<
1,
0;
1$
#4740000
1(
1&
1#
0)
0@
0Z
0A
1K
0?
0X
12
0>
1.
1=
0-
1<
0,
1;
0$
#4770000
0(
0&
1)
1@
1Z
0K
1?
1X
02
1>
0.
0=
1-
0<
1,
0;
0%
1$
#4800000
1(
1&
1#
0)
0@
0Z
0A
1K
0?
0X
12
0>
1.
1=
0-
1<
0,
1;
0$
#4830000
0(
0&
1)
1@
1Z
0K
1?
1X
02
1>
0.
0=
1-
0<
1,
0;
1%
1$
#4860000
1(
1&
1#
0)
0@
0Z
0A
1K
0?
0X
12
0>
1.
1=
0-
1<
0,
1;
0$
#4890000
0(
0&
1)
1@
1Z
0K
1?
1X
02
1>
0.
0=
1-
0<
1,
0;
1$
#4920000
1(
1&
1#
0)
0@
0Z
0A
1K
0?
0X
12
0>
1.
1=
0-
1<
0,
1;
0$
#4950000
0(
0&
1)
1@
1Z
0K
1?
1X
02
1>
0.
0=
1-
0<
1,
0;
1$
#4980000
1(
1&
1#
0)
0@
0Z
0A
1K
0?
0X
12
0>
1.
1=
0-
1<
0,
1;
0$
#5010000
0(
0&
1)
1@
1Z
0K
1?
1X
02
1>
0.
0=
1-
0<
1,
0;
0%
1$
#5040000
1(
1&
1#
0)
0@
0Z
0A
1K
0?
0X
12
0>
1.
1=
0-
1<
0,
1;
0$
#5070000
0(
0&
1)
1@
1Z
0K
1?
1X
02
1>
0.
0=
1-
0<
1,
0;
1%
1$
#5100000
1(
1&
1#
0)
0@
0Z
0A
1K
0?
0X
12
0>
1.
1=
0-
1<
0,
1;
0$
#5130000
0(
0&
1)
1@
1Z
0K
1?
1X
02
1>
0.
0=
1-
0<
1,
0;
1$
#5160000
1(
1&
1#
0)
0@
0Z
0A
1K
0?
0X
12
0>
1.
1=
0-
1<
0,
1;
0$
#5190000
0(
0&
1)
1@
1Z
0K
1?
1X
02
1>
0.
0=
1-
0<
1,
0;
0%
1$
#5220000
1(
1&
1#
0)
0@
0Z
0A
1K
0?
0X
12
0>
1.
1=
0-
1<
0,
1;
0$
#5250000
0(
0&
1)
1@
1Z
0K
1?
1X
02
1>
0.
0=
1-
0<
1,
0;
1$
#5280000
1(
1&
1#
0)
0@
0Z
0A
1K
0?
0X
12
0>
1.
1=
0-
1<
0,
1;
0$
#5310000
0(
0&
1)
1@
1Z
0K
1?
1X
02
1>
0.
0=
1-
0<
1,
0;
1$
#5340000
1(
1&
1#
0)
0@
0Z
0A
1K
0?
0X
12
0>
1.
1=
0-
1<
0,
1;
0$
#5370000
0(
0&
1)
1@
1Z
0K
1?
1X
02
1>
0.
0=
1-
0<
1,
0;
1$
#5400000
1(
1&
1#
0)
0@
0Z
0A
1K
0?
0X
12
0>
1.
1=
0-
1<
0,
1;
0$
#5430000
0(
0&
1)
1@
1Z
0K
1?
1X
02
1>
0.
0=
1-
0<
1,
0;
1%
1$
#5460000
1(
1&
1#
0)
0@
0Z
0A
1K
0?
0X
12
0>
1.
1=
0-
1<
0,
1;
0$
#5490000
0(
0&
1)
1@
1Z
0K
1?
1X
02
1>
0.
0=
1-
0<
1,
0;
1$
#5520000
1(
1&
1#
0)
0@
0Z
0A
1K
0?
0X
12
0>
1.
1=
0-
1<
0,
1;
0$
#5550000
0(
0&
1)
1@
1Z
0K
1?
1X
02
1>
0.
0=
1-
0<
1,
0;
0%
1$
#5580000
1(
1&
1#
0)
0@
0Z
0A
1K
0?
0X
12
0>
1.
1=
0-
1<
0,
1;
0$
#5610000
0(
0&
1)
1@
1Z
0K
1?
1X
02
1>
0.
0=
1-
0<
1,
0;
1$
#5640000
1(
1&
1#
0)
0@
0Z
0A
1K
0?
0X
12
0>
1.
1=
0-
1<
0,
1;
0$
#5670000
0(
0&
1)
1@
1Z
0K
1?
1X
02
1>
0.
0=
1-
0<
1,
0;
1%
1$
#5700000
1(
1&
1#
0)
0@
0Z
0A
1K
0?
0X
12
0>
1.
1=
0-
1<
0,
1;
0$
#5730000
0(
0&
1)
1@
1Z
0K
1?
1X
02
1>
0.
0=
1-
0<
1,
0;
1$
#5760000
1(
1&
1#
0)
0@
0Z
0A
1K
0?
0X
12
0>
1.
1=
0-
1<
0,
1;
0$
#5790000
0(
0&
1)
1@
1Z
0K
1?
1X
02
1>
0.
0=
1-
0<
1,
0;
1$
#5820000
1(
1&
1#
0)
0@
0Z
0A
1K
0?
0X
12
0>
1.
1=
0-
1<
0,
1;
0$
#5850000
0(
0&
1)
1@
1Z
0K
1?
1X
02
1>
0.
0=
1-
0<
1,
0;
1$
#5880000
1(
1&
1#
0)
0@
0Z
0A
1K
0?
0X
12
0>
1.
1=
0-
1<
0,
1;
0$
#5910000
0(
0&
1)
1@
1Z
0K
1?
1X
02
1>
0.
0=
1-
0<
1,
0;
1$
#5940000
1(
1&
1#
0)
0@
0Z
0A
1K
0?
0X
12
0>
1.
1=
0-
1<
0,
1;
0$
#5970000
0(
0&
1)
1@
1Z
0K
1?
1X
02
1>
0.
0=
1-
0<
1,
0;
0%
1$
#6000000
1(
1&
1#
0)
0@
0Z
0A
1K
0?
0X
12
0>
1.
1=
0-
1<
0,
1;
0$
#6030000
0(
0&
1)
1@
1Z
0K
1?
1X
02
1>
0.
0=
1-
0<
1,
0;
1%
1$
#6060000
1(
1&
1#
0)
0@
0Z
0A
1K
0?
0X
12
0>
1.
1=
0-
1<
0,
1;
0$
#6090000
0(
0&
1)
1@
1Z
0K
1?
1X
02
1>
0.
0=
1-
0<
1,
0;
1$
#6120000
1(
1&
1#
0)
0@
0Z
0A
1K
0?
0X
12
0>
1.
1=
0-
1<
0,
1;
0$
#6150000
0(
0&
1)
1@
1Z
0K
1?
1X
02
1>
0.
0=
1-
0<
1,
0;
1$
#6180000
1(
1&
1#
0)
0@
0Z
0A
1K
0?
0X
12
0>
1.
1=
0-
1<
0,
1;
0$
#6210000
0(
0&
1)
1@
1Z
0K
1?
1X
02
1>
0.
0=
1-
0<
1,
0;
0%
1$
#6240000
1(
1&
1#
0)
0@
0Z
0A
1K
0?
0X
12
0>
1.
1=
0-
1<
0,
1;
0$
#6270000
0(
0&
1)
1@
1Z
0K
1?
1X
02
1>
0.
0=
1-
0<
1,
0;
1$
#6300000
1(
1&
1#
0)
0@
0Z
0A
1K
0?
0X
12
0>
1.
1=
0-
1<
0,
1;
0$
#6330000
0(
0&
1)
1@
1Z
0K
1?
1X
02
1>
0.
0=
1-
0<
1,
0;
1$
#6360000
1(
1&
1#
0)
0@
0Z
0A
1K
0?
0X
12
0>
1.
1=
0-
1<
0,
1;
0$
#6390000
0(
0&
1)
1@
1Z
0K
1?
1X
02
1>
0.
0=
1-
0<
1,
0;
1$
#6420000
1(
1&
1#
0)
0@
0Z
0A
1K
0?
0X
12
0>
1.
1=
0-
1<
0,
1;
0$
#6450000
0(
0&
1)
1@
1Z
0K
1?
1X
02
1>
0.
0=
1-
0<
1,
0;
1$
#6480000
1(
1&
1#
0)
0@
0Z
0A
1K
0?
0X
12
0>
1.
1=
0-
1<
0,
1;
0$
#6510000
0(
0&
1)
1@
1Z
0K
1?
1X
02
1>
0.
0=
1-
0<
1,
0;
1$
#6540000
1(
1&
1#
0)
0@
0Z
0A
1K
0?
0X
12
0>
1.
1=
0-
1<
0,
1;
0$
#6570000
0(
0&
1)
1@
1Z
0K
1?
1X
02
1>
0.
0=
1-
0<
1,
0;
1$
